Workbook

Sheet orgNodes
A1: entityID | B1: entity | C1: tier1and2entity | D1: tier1and2entityID | E1: entityIDAbove | F1: mission | G1: website | H1: operational | I1: decision | J1: regulatory | K1: research | L1: level
A2: n01 | B2: Texas | C2: Texas | D2: 1 | E2: NA | G2: https://texas.gov/ | H2: Yes | I2: Yes | J2: Yes | K2: Yes | L2: 1
A3: n02 | B3: Department of Agriculture | C3: Department of Agriculture | D3: 2 | E3: n01 | F3: Partner with all Texans to make Texas the nation's leader in agriculture, fortify our economy, empower rural communities, promote healthy lifestyles, and cultivate winning strategies for rural, suburban and urban Texas through exceptional service and the common threads of agriculture in our daily lives. | G3: http://www.texasagriculture.gov/Home.aspx | H3: Yes | I3: Yes | J3: No | K3: No | L3: 2
A4: n03 | B4: Department of Parks and Wildlife | C4: Department of Parks and Wildlife | D4: 3 | E4: n01 | F4: Manage and conserve the natural and cultural resources of Texas and to provide hunting, fishing and outdoor recreation opportunities for the use and enjoyment of present and future generations. | G4: https://tpwd.texas.gov/ | H4: No | I4: Yes | J4: Yes | K4: Yes | L4: 2
A5: n04 | B5: Coastal Fisheries Division | C5: Department of Parks and Wildlife | D5: 3 | E5: n03 | F5: Manage the marine fishery resources of Texas' four million acres of saltwater, including the bays and estuaries and out to nine nautical miles in the Gulf of Mexico. | G5: https://tpwd.texas.gov/about/administration-divisions/coastal-fisheries | H5: No | I5: Yes | J5: Yes | K5: Yes | L5: 3
A6: n05 | B6: Water Resources | C6: Department of Parks and Wildlife | D6: 3 | E6: n04 | F6: Provide technical and policy expertise to the agency and external stakeholders for addressing environmental water issues. | G6: https://tpwd.texas.gov/landwater/water/conservation/water_resources/index.phtml | H6: No | I6: Yes | J6: Yes | K6: Yes | L6: 4
A7: n06 | B7: Water Quantity | C7: Department of Parks and Wildlife | D7: 3 | E7: n05 | F7: Deal with various aspects of water right permitting, planning, and policy seeking to maintain a sufficient flow of water in Texas rivers and streams and freshwater inflows to bays and estuaries for the benefit of ecologically and economically important fish and wildlife. | G7: https://tpwd.texas.gov/landwater/water/conservation/water_resources/water_quantity/index.phtml | H7: No | I7: Yes | J7: Yes | K7: Yes | L7: 5
A8: n07 | B8: Water Quality | C8: Department of Parks and Wildlife | D8: 3 | E8: n05 | F8: Work with local, state and federal agencies to ensure that the needs of fish, wildlife, and aquatic resources are considered in water quality planning and permitting activities at both statewide and local levels. | G8: https://tpwd.texas.gov/landwater/water/environconcerns/water_quality/index.phtml | H8: No | I8: Yes | J8: Yes | K8: No | L8: 5
A9: n08 | B9: River Studies | C9: Department of Parks and Wildlife | D9: 3 | E9: n05 | F9: River Studies is an interdisciplinary river and stream assessment program with the goal of assuring sufficient quantity and quality of water to maintain the natural biodiversity of aquatic ecosystems and their associated wetlands and riparian lands. | G9: https://tpwd.texas.gov/landwater/water/conservation/fwresources/ | H9: No | I9: Yes | J9: No | K9: Yes | L9: 5
A10: n09 | B10: Texas Commission on Environmental Quality | C10: Texas Commission on Environmental Quality | D10: 4 | E10: n01 | F10: Strive to protect our state's public health and natural resources consistent with sustainable economic development. | G10: https://www.tceq.texas.gov/ | H10: Yes | I10: Yes | J10: Yes | K10: Yes | L10: 2
A11: n10 | B11: Water | C11: Texas Commission on Environmental Quality | D11: 4 | E11: n09 | F11: Maintaining water quality and availability for municipalities, businesses, and homeowners. | G11: https://www.tceq.texas.gov/agency/water_main.html | H11: Yes | I11: Yes | J11: Yes | K11: Yes | L11: 3
A12: n11 | B12: Water Availability | C12: Texas Commission on Environmental Quality | D12: 4 | E12: n10 | F12: Responsible for ensuring the waters of the state are managed in accordance with the Texas Water Code, and for undertaking activities to protect and assess our groundwater resources. | G12: https://www.tceq.texas.gov/agency/organization/water.html#wateravail | H12: No | I12: Yes | J12: Yes | K12: No | L12: 4
A13: n12 | B13: Water Quality | C13: Texas Commission on Environmental Quality | D13: 4 | E13: n10 | F13: Protecting the quality of water in Texas. | G13: https://www.tceq.texas.gov/agency/organization/water.html#waterquality | H13: No | I13: Yes | J13: No | K13: No | L13: 4
A14: n13 | B14: Water Quality Planning | C14: Texas Commission on Environmental Quality | D14: 4 | E14: n10 | F14: Assess, protect, and improve the quality of Texas surface water resources. | G14: https://www.tceq.texas.gov/agency/organization/water.html#waterplanning | H14: No | I14: Yes | J14: Yes | K14: No | L14: 4
... A25: n24 | B25: Texas Water Development Board | C25: Texas Water Development Board | D25: 6 | E25: n01 | F25: Provide leadership, information, education, and support for planning, financial assistance, and outreach for the conservation and responsible development of water for Texas. | G25: http://www.twdb.texas.gov/index.asp | H25: Yes | I25: Yes | J25: Yes | K25: Yes | L25: 2
A26: n25 | B26: Water Supply and Infrastructure | C26: Texas Water Development Board | D26: 6 | E26: n24 | H26: Yes | I26: Yes | J26: Yes | K26: No | L26: 3
A27: n26 | B27: Water Use, Projections and Planning | C27: Texas Water Development Board | D27: 6 | E27: n25 | F27: Collecting, analyzing, and disseminating water-related data; and, by providing other services necessary to aid in planning and managing the state's water resources. | G27: http://www.twdb.texas.gov/waterplanning/index.asp | H27: No | I27: Yes | J27: Yes | K27: No | L27: 4
A28: n27 | B28: Regional Water Planning | C28: Texas Water Development Board | D28: 6 | E28: n26 | F28: Guide and support planning of the state's water resources by administering and assisting in the development of the regional and state water plans. | G28: http://www.twdb.texas.gov/waterplanning/rwp/index.asp | H28: No | I28: Yes | J28: Yes | K28: No | L28: 5
A29: n28 | B29: Water Use Survey | C29: Texas Water Development Board | D29: 6 | E29: n26 | F29: Collect annual water use data to support the development and management of the water resources of Texas | G29: http://www.twdb.texas.gov/waterplanning/waterusesurvey/index.asp | H29: No | I29: Yes | J29: No | K29: No | L29: 5
A30: n29 | B30: Water Science and Conservation | C30: Texas Water Development Board | D30: 6 | E30: n24 | F30: To provide leadership, planning, education, information, technical assistance, and agricultural financial assistance for water conservation in Texas. | G30: http://www.twdb.texas.gov/conservation/index.asp | H30: No | I30: Yes | J30: Yes | K30: Yes | L30: 3
A31: n30 | B31: Conservation and Innovative Water Technologies | C31: Texas Water Development Board | D31: 6 | E31: n29 | H31: No | I31: Yes | J31: Yes | K31: Yes | L31: 4
A32: n31 | B32: Municipal Water Conservation | C32: Texas Water Development Board | D32: 6 | E32: n30 | F32: To provide services that help Texans establish effective municipal water conservation programs by implementing best management practices. | G32: http://www.twdb.texas.gov/conservation/municipal/index.asp | H32: No | I32: No | J32: Yes | K32: No | L32: 5
A33: n32 | B33: Innovative Water Technologies | C33: Texas Water Development Board | D33: 6 | E33: n30 | F33: Educate the water community on the use of nontraditional water supplies. | G33: http://www.twdb.texas.gov/innovativewater/ | H33: No | I33: No | J33: No | K33: Yes | L33: 5
A34: n33 | B34: Surface Water | C34: Texas Water Development Board | D34: 6 | E34: n29 | F34: Provides scientific and engineering expertise associated with data collection, analysis and modeling of surface waters in Texas to ensure the continued availability of water supplies and the maintenance of the ecological health and productivity of Texas rivers, streams, reservoirs, bays and estuaries. | G34: http://www.twdb.texas.gov/surfacewater/index.asp | H34: No | I34: Yes | J34: No | K34: Yes | L34: 4
A35: n34 | B35: TexMesonet and Hydrosurvey | C35: Texas Water Development Board | D35: 6 | E35: n33 | F35: To create a unified virtual network of high quality data to support flood monitoring and flood forecasting efforts by the National Weather Service, regional river authorities, and local emergency responders. | G35: https://www.texmesonet.org/ | H35: No | I35: Yes | J35: No | K35: No | L35: 5
A36: n35 | B36: Water Data for Texas | C36: Texas Water Development Board | D36: 6 | E36: n33 | F36: To provide a single access point for customers to receive water-related data. | G36: http://www.twdb.texas.gov/surfacewater/conditions/index.asp | H36: No | I36: Yes | J36: No | K36: No | L36: 5
A37: n36 | B37: Groundwater | C37: Texas Water Development Board | D37: 6 | E37: n29 | F37: Collect, interpret, and provide accurate, objective information on the groundwater resources of Texas. | G37: http://www.twdb.texas.gov/groundwater/index.asp | H37: No | I37: Yes | J37: No | K37: No | L37: 4
A38: n37 | B38: Groundwater Monitoring | C38: Texas Water Development Board | D38: 6 | E38: n36 | F38: To monitor changes in the quality of groundwater over time and to establish as accurately as possible the baseline quality of groundwater occurring naturally in the state's aquifers. | G38: http://www.twdb.texas.gov/groundwater/data/index.asp | H38: No | I38: Yes | J38: No | K38: No | L38: 5
A39: n38 | B39: Texas Natural Resources Information System | C39: Texas Water Development Board | D39: 6 | E39: n24 | F39: A reliable and unique state resource that provides high quality historic and current geospatial data products, education and training, while advancing the GIS Community through collaboration, expertise, cost-sharing initiatives and exceptional customer service. | G39: https://tnris.org/ | H39: No | I39: Yes | J39: No | K39: No | L39: 3
A40: n39 | B40: Strategic Mapping | C40: Texas Water Development Board | D40: 6 | E40: n38 | F40: Acquire and improve digital geographic data for statewide mapping applications. | G40: https://tnris.org/stratmap/ | H40: No | I40: Yes | J40: No | K40: No | L40: 4
A41: n40 | B41: Angelina and Neches River Authority | C41: Angelina and Neches River Authority | D41: 7 | E41: n01 | F41: Conserve, store, control, preserve, use, and distribute the storm water, floodwater and the water of the rivers and streams of the state in the Neches River Basin for the benefit of the human environment and the natural environment. | G41: https://www.anra.org/index.html | H41: Yes | I41: Yes | J41: Yes | K41: No | L41: 2
A42: n41 | B42: Water Quality | C42: Angelina and Neches River Authority | D42: 7 | E42: n40 | G42: https://www.anra.org/divisions/water_quality/index.html | H42: No | I42: Yes | J42: No | K42: No | L42: 3
A43: n42 | B43: Water Delivery | C43: Angelina and Neches River Authority | D43: 7 | E43: n40 | G43: https://www.anra.org/divisions/water_delivery/index.html | H43: Yes | I43: No | J43: No | K43: No | L43: 3
A44: n43 | B44: Wastewater | C44: Angelina and Neches River Authority | D44: 7 | E44: n40 | G44: https://www.anra.org/divisions/wastewater/index.html | H44: Yes | I44: No | J44: Yes | K44: No | L44: 3
A45: n44 | B45: Reservoirs | C45: Angelina and Neches River Authority | D45: 7 | E45: n40 | G45: https://www.anra.org/divisions/reservoirs/index.html | H45: Yes | I45: No | J45: Yes | K45: No | L45: 3
A46: n45 | B46: Bandera County River Authority | C46: Bandera County River Authority | D46: 8 | E46: n01 | F46: Protect and preserve the county's water and natural resources for the state of Texas. | G46: http://www.bcragd.org/ | H46: Yes | I46: Yes | J46: Yes | K46: No | L46: 2
A47: n46 | B47: Groundwater | C47: Bandera County River Authority | D47: 8 | E47: n45 | H47: No | I47: Yes | J47: No | K47: No | L47: 3
A48: n47 | B48: Medina Lake | C48: Bandera County River Authority | D48: 8 | E48: n46 | F48: Protect and preserve the resource for the people of our community and downstream communities who utilize the waters of the Medina every day. | G48: http://www.bcragd.org/medina-lake/ | H48: No | I48: Yes | J48: No | K48: No | L48: 5
A49: n48 | B49: Surface Water | C49: Bandera County River Authority | D49: 8 | E49: n45 | H49: No | I49: Yes | J49: No | K49: No | L49: 3
A50: n49 | B50: Water Quality Monitoring Program | C50: Bandera County River Authority | D50: 8 | E50: n48 | F50: Field technicians sample water quality of the Medina River, Medina Lake, and its tributaries quarterly to assess E.coli concentrations. | G50: http://www.bcragd.org/water-quality-testing/ | H50: No | I50: Yes | J50: No | K50: No | L50: 5
A51: n50 | B51: Flood Management | C51: Bandera County River Authority | D51: 8 | E51: n45 | H51: Yes | I51: No | J51: No | K51: No | L51: 3
A52: n51 | B52: Brazos River Authority | C52: Brazos River Authority | D52: 9 | E52: n01 | F52: Develop, manage and protect the water resources of the Brazos River basin. | G52: http://www.brazos.org/ | H52: Yes | I52: Yes | J52: Yes | K52: No | L52: 2
A53: n52 | B53: Reservoirs | C53: Brazos River Authority | D53: 9 | E53: n51 | F53: The Brazos River Authority water supply system includes 11 reservoirs scattered across the 42,000 square mile river basin. | G53: http://www.brazos.org/About-Us/Reservoirs | H53: Yes | I53: Yes | J53: Yes | K53: No | L53: 3
A54: n53 | B54: Water Supply | C54: Brazos River Authority | D54: 9 | E54: n51 | F54: The BRA currently holds water rights issued by the State of Texas for a System of reservoirs. Collectively, these rights authorize the BRA to supply approximately one million acre-feet of water from the Brazos River basin annually for municipal, industrial, agricultural and mining purposes. | G54: http://www.brazos.org/About-Us/Water-Supply | H54: Yes | I54: Yes | J54: Yes | K54: No | L54: 3
A55: n54 | B55: Drought | C55: Brazos River Authority | D55: 9 | E55: n53 | F55: Project reservoir drawdowns during drought. | G55: http://www.brazos.org/About-Us/Water-Supply/Drought | H55: Yes | I55: No | J55: No | K55: No | L55: 4
A56: n55 | B56: Contracting | C56: Brazos River Authority | D56: 9 | E56: n53 | F56: Oversees five types of water supply contracts throughout the Brazos River Basin. | G56: http://www.brazos.org/About-Us/Water-Supply/Contracting | H56: No | I56: Yes | J56: Yes | K56: No | L56: 4
A57: n56 | B57: Water Quality | C57: Brazos River Authority | D57: 9 | E57: n51 | F57: The Brazos River Authority works with state and federal authorities to monitor the quality of Brazos River basin surface water while providing clean, potable drinking water as well as wastewater services to the people of the Brazos basin. | G57: http://www.brazos.org/About-Us/Water-Quality | H57: No | I57: Yes | J57: No | K57: No | L57: 3
A58: n57 | B58: Clean Rivers Program | C58: Brazos River Authority | D58: 9 | E58: n56 | F58: The Clean Rivers Act requires an ongoing assessment of water quality issues and management strategies statewide to guide Texas water resources policy and decision-making into the 21st Century | G58: http://www.brazos.org/About-Us/Water-Quality/Clean-Rivers-Program | H58: No | I58: Yes | J58: No | K58: No | L58: 5
A59: n58 | B59: BrazosBasinNOW | C59: Brazos River Authority | D59: 9 | E59: n51 | F59: BrazosBasinNOW is the Brazos River Authority’s new River and Reservoir information web page featuring streamflow, reservoir and rainfall maps in a map-based, gage-system format | G59: https://www.brazosbasinnow.org/home.php | H59: Yes | I59: No | J59: No | K59: No | L59: 3
A60: n59 | B60: Guadalupe Blanco River Authority | C60: Guadalupe Blanco River Authority | D60: 10 | E60: n01 | F60: Support responsible watershed protection and stewardship, provide quality operational service, and a commitment to promote conservation and educational opportunities in order to enhance quality of life for those we serve. | G60: http://www.gbra.org/ | H60: Yes | I60: Yes | J60: No | K60: No | L60: 2
A61: n60 | B61: Hydroelectric Generation | C61: Guadalupe Blanco River Authority | D61: 10 | E61: n59 | H61: Yes | I61: No | J61: No | K61: No | L61: 3
A62: n61 | B62: Wastewater Treatment | C62: Guadalupe Blanco River Authority | D62: 10 | E62: n59 | H62: Yes | I62: No | J62: No | K62: No | L62: 3
A63: n62 | B63: Water Resource Management | C63: Guadalupe Blanco River Authority | D63: 10 | E63: n59 | H63: No | I63: Yes | J63: No | K63: No | L63: 3
A64: n63 | B64: Clean Rivers Program | C64: Guadalupe Blanco River Authority | D64: 10 | E64: n60 | G64: http://www.gbra.org/crp/default.aspx | H64: No | I64: Yes | J64: No | K64: No | L64: 5
A65: n64 | B65: Lavaca Navidad River Authority | C65: Lavaca Navidad River Authority | D65: 11 | E65: n01 | F65: Water for today and tomorrow | G65: http://www.lnra.org/ | H65: Yes | I65: Yes | J65: No | K65: No | L65: 2
A66: n65 | B66: Water Delivery | C66: Lavaca Navidad River Authority | D66: 11 | E66: n64 | F66: Oversees the delivery of raw water. | H66: Yes | I66: No | J66: No | K66: No | L66: 3
A67: n66 | B67: Environmental Services | C67: Lavaca Navidad River Authority | D67: 11 | E67: n64 | F67: Conducts monthly monitoring of water quality field data and quarterly sampling of water chemistry at sites throughout Lavaca Basin. | H67: No | I67: Yes | J67: No | K67: No | L67: 3
A68: n67 | B68: Reservoir | C68: Lavaca Navidad River Authority | D68: 11 | E68: n64 | F68: Provide for the safe and efficient operation and maintenance of the Palmetto Bend Dam and Spillway Structures. | H68: Yes | I68: No | J68: No | K68: No | L68: 3
A69: n68 | B69: Lower Colorado River Authority | C69: Lower Colorado River Authority | D69: 12 | E69: n01 | F69: To enhance the quality of life of the Texans we serve through water stewardship, energy and community service. | G69: https://www.lcra.org/Pages/default.aspx | H69: Yes | I69: Yes | J69: Yes | K69: No | L69: 2
A70: n69 | B70: Water | C70: Lower Colorado River Authority | D70: 12 | E70: n68 | F70: Providing water for more than a million people | G70: https://www.lcra.org/water/Pages/default.aspx | H70: Yes | I70: Yes | J70: Yes | K70: No | L70: 3
A71: n70 | B71: Water Resources | C71: Lower Colorado River Authority | D71: 12 | E71: n69 | H71: Yes | I71: Yes | J71: Yes | K71: No | L71: 4
A72: n71 | B72: Water Resource Planning | C72: Lower Colorado River Authority | D72: 12 | E72: n70 | H72: No | I72: Yes | J72: Yes | K72: No | L72: 5
A73: n72 | B73: Water Conservation | C73: Lower Colorado River Authority | D73: 12 | E73: n70 | H73: No | I73: Yes | J73: No | K73: No | L73: 5
A74: n73 | B74: Water Quality Protection | C74: Lower Colorado River Authority | D74: 12 | E74: n70 | H74: No | I74: Yes | J74: No | K74: No | L74: 5
A75: n74 | B75: Water Operations | C75: Lower Colorado River Authority | D75: 12 | E75: n69 | H75: Yes | I75: Yes | J75: Yes | K75: No | L75: 4
A76: n75 | B76: River Operations | C76: Lower Colorado River Authority | D76: 12 | E76: n74 | H76: Yes | I76: No | J76: No | K76: No | L76: 5
A77: n76 | B77: Irrigation Operations | C77: Lower Colorado River Authority | D77: 12 | E77: n74 | H77: Yes | I77: No | J77: No | K77: No | L77: 5
A78: n77 | B78: Dams and Hydro | C78: Lower Colorado River Authority | D78: 12 | E78: n74 | H78: Yes | I78: No | J78: Yes | K78: No | L78: 5
A79: n78 | B79: River Surface Management | C79: Lower Colorado River Authority | D79: 12 | E79: n74 | H79: Yes | I79: No | J79: No | K79: No | L79: 5
A80: n79 | B80: Transmission | C80: Lower Colorado River Authority | D80: 12 | E80: n68 | H80: No | I80: Yes | J80: No | K80: No | L80: 3
A81: n80 | B81: Lower Neches Valley Authority | C81: Lower Neches Valley Authority | D81: 13 | E81: n01 | F81: Provides for the present and long term freshwater needs of municipal, agricultural and industrial customers, protects water quality in the Neches River and Coastal Basin, insures affordability of the water supply, and enhances economic development in the Authoritys jurisdiction. | G81: http://lnva.dst.tx.us/ | H81: No | I81: Yes | J81: No | K81: No | L81: 2
A82: n81 | B82: Nueces River Authority | C82: Nueces River Authority | D82: 14 | E82: n01 | F82: We have broad authority to develop water resources, provide for flood control and irrigation, develop parks, finance water supply and pollution control projects, and receive state and federal grants and loans. | G82: http://www.nueces-ra.org/ | H82: Yes | I82: Yes | J82: Yes | K82: No | L82: 2
A83: n82 | B83: Water Quality Programs | C83: Nueces River Authority | D83: 14 | E83: n81 | G83: https://www.nueces-ra.org/CP/ | H83: No | I83: Yes | J83: No | K83: No | L83: 3
A84: n83 | B84: Resource Protection & Education | C84: Nueces River Authority | D84: 14 | E84: n81 | H84: Yes | I84: Yes | J84: No | K84: No | L84: 3
A85: n84 | B85: Red River Authority | C85: Red River Authority | D85: 15 | E85: n01 | F85: Orderly conservation, reclamation, protection, and development of the water resources throughout the Red River Basin for the benefit of the public. | G85: http://www.rra.texas.gov/ | H85: Yes | I85: Yes | J85: Yes | K85: No | L85: 2
A86: n85 | B86: General Services Branch | C86: Red River Authority | D86: 15 | E86: n84 | F86: To provide budget and personnel administration, project and program development and management, information resource management, cartographic mapping and technical support, and performance monitoring for all agency related activities and services. | H86: Yes | I86: Yes | J86: No | K86: No | L86: 3
A87: n86 | B87: General Operations Branch | C87: Red River Authority | D87: 15 | E87: n84 | H87: Yes | I87: Yes | J87: Yes | K87: No | L87: 3
A88: n87 | B88: Utility Division | C88: Red River Authority | D88: 15 | E88: n86 | F88: To provide water and sewer services for rural unincorporated communities, towns and cities within a 15 county area of North Texas. | H88: Yes | I88: Yes | J88: Yes | K88: No | L88: 4
A89: n88 | B89: Environmental Services Division | C89: Red River Authority | D89: 15 | E89: n86 | F89: The principal purpose of the ESD is to control and / or abate any possible threat of pollution to the environment and the water resources | H89: No | I89: Yes | J89: No | K89: No | L89: 4
A90: n89 | B90: Sabine River Authority | C90: Sabine River Authority | D90: 16 | E90: n01 | F90: Control, store, preserve, and distribute the waters of the Sabine River and its tributary system for useful purposes. | G90: http://www.sratx.org/ | H90: Yes | I90: Yes | J90: No | K90: No | L90: 2
A91: n90 | B91: Environmental Services Division | C91: Sabine River Authority | D91: 16 | E91: n89 | F91: Provide field and laboratory services for SRA-TX, as well as governmental entities, industries and municipalities. | G91: http://www.sratx.org/aboutsra/esd.asp | H91: No | I91: Yes | J91: No | K91: No | L91: 3
A92: n91 | B92: San Antonio River Authority | C92: San Antonio River Authority | D92: 17 | E92: n01 | F92: Committed to Safe, Clean, Enjoyable Creeks and Rivers. | G92: https://www.sara-tx.org/ | H92: Yes | I92: Yes | J92: Yes | K92: Yes | L92: 2
A93: n92 | B93: Environmental Sciences | C93: San Antonio River Authority | D93: 17 | E93: n91 | F93: Provides research, data gathering, scientific assessment and environmental coordination functions for the San Antonio River Authority. | G93: https://www.sara-tx.org/environmental-science/ | H93: No | I93: Yes | J93: No | K93: Yes | L93: 3
A94: n93 | B94: Public Services & Resources | C94: San Antonio River Authority | D94: 17 | E94: n91 | F94: Serves as a regional constituency for water and wastewater | G94: https://www.sara-tx.org/public-services/ | H94: Yes | I94: Yes | J94: Yes | K94: No | L94: 3
A95: n94 | B95: Flood Management | C95: San Antonio River Authority | D95: 17 | E95: n91 | F95: Advocates a regional approach to flood control issues. | G95: https://www.sara-tx.org/flood-management/ | H95: Yes | I95: No | J95: No | K95: No | L95: 3
A96: n95 | B96: Utilities | C96: San Antonio River Authority | D96: 17 | E96: n94 | F96: Serves as a full-service water and wastewater utility provider within its district | G96: https://www.sara-tx.org/public-services/utilities/ | H96: Yes | I96: Yes | J96: Yes | K96: No | L96: 4
A97: n96 | B97: San Jacinto River Authority | C97: San Jacinto River Authority | D97: 18 | E97: n01 | F97: Provide reliable, cost-efficient, and sustainable water resource management that supports economic and industrial growth in the region and earns the trust and confidence of SJRAs customers. | G97: http://www.sjra.net/ | H97: Yes | I97: Yes | J97: Yes | K97: No | L97: 2
A98: n97 | B98: Lake Conroe Division | C98: San Jacinto River Authority | D98: 18 | E98: n96 | F98: Municipal and industrial raw water supply, reservoir operations, water quality and source water protection, invasive species management, navigational safety, and regulation of structures on the reservoir. | G98: http://www.sjra.net/lakeconroe/ | H98: Yes | I98: Yes | J98: Yes | K98: No | L98: 3
A99: n98 | B99: Woodlands Division | C99: San Jacinto River Authority | D99: 18 | E99: n96 | F99: Dedicated to excellence in developing and maintaining a superior water and wastewater system to meet the needs of our community. | G99: http://www.sjra.net/woodlands/ | H99: Yes | I99: Yes | J99: Yes | K99: No | L99: 3
A100: n99 | B100: Highlands Division | C100: San Jacinto River Authority | D100: 18 | E100: n96 | F100: Delivers more water each day than all other SJRA divisions combined. | G100: http://www.sjra.net/highlands/ | H100: Yes | I100: Yes | J100: Yes | K100: No | L100: 3
A101: n100 | B101: Reduction Plan Division | C101: San Jacinto River Authority | D101: 18 | E101: n96 | F101: Implementing a countywide program that will meet the requirements of the Lone Star Groundwater Conservation District to substantially reduce future groundwater usage from the Gulf Coast Aquifer by ensuring a reliable, long-term diversified portfolio of alternative water supply sources for all of Montgomery County. | G101: http://www.sjra.net/grp/ | H101: No | I101: Yes | J101: No | K101: No | L101: 3
... A103: n102 | B103: Sulphur River Basin Authority | C103: Sulphur River Authority | D103: 19 | E103: n01 | F103: Provide for the conservation and development of the states natural resources within the basin of the Sulphur River. | G103: http://srbatx.org/ | H103: No | I103: Yes | J103: No | K103: No | L103: 2
A104: n103 | B104: Clean Rivers Program | C104: Sulphur River Authority | D104: 19 | E104: n102 | G104: http://sulphurr.org/ | H104: No | I104: Yes | J104: No | K104: No | L104: 5
A105: n104 | B105: Trinity River Authority | C105: Trinity River Authority | D105: 20 | E105: n01 | F105: Promote conservation, reclamation, protection and development of the natural resources of the river basin for the benefit of the public. | G105: http://www.trinityra.org/ | H105: No | I105: Yes | J105: No | K105: No | L105: 2
A106: n105 | B106: Planning & Environmental Management | C106: Trinity River Authority | D106: 20 | E106: n104 | F106: Prepare and maintain a master plan for responsible water use. | G106: http://www.trinityra.org/basin-planning.htm | H106: No | I106: Yes | J106: No | K106: No | L106: 3
A107: n106 | B107: Upper Colorado River Authority | C107: Upper Colorado River Authority | D107: 21 | E107: n01 | F107: Enhance the water quality of the streams and tributaries located within the watershed of the Upper Colorado River Authority. | G107: http://www.ucratx.org/index.html | H107: No | I107: Yes | J107: No | K107: No | L107: 2
A108: n107 | B108: Clean Rivers Program | C108: Upper Colorado River Authority | D108: 21 | E108: n107 | G108: http://www.ucratx.org/crp.html | H108: No | I108: Yes | J108: No | K108: No | L108: 5
A109: n108 | B109: Upper Guadalupe River Authority | C109: Upper Guadalupe River Authority | D109: 22 | E109: n01 | F109: Protect, develop, and manage the water quantity, quality, and sustainability in the Guadalupe River watershed in Kerr County. | G109: http://www.ugra.org/ | H109: No | I109: Yes | J109: No | K109: No | L109: 2
A110: n109 | B110: Department of State Health Services | C110: Department of State Health Services | D110: 23 | E110: n01 | F110: Improve the health, safety, and well-being of Texans through good stewardship of public resources, and a focus on core public health functions. | G110: http://www.dshs.texas.gov/ | H110: Yes | I110: Yes | J110: Yes | K110: Yes | L110: 2
A111: n110 | B111: Environmental and Injury Epidemiology and Toxicology | C111: Department of State Health Services | D111: 23 | E111: n109 | G111: http://www.dshs.texas.gov/epitox/default.shtm | H111: Yes | I111: Yes | J111: Yes | K111: Yes | L111: 3
...

Sheet orgEdges
A1: from | B1: to
A2: n01 | B2: n02
A3: n01 | B3: n03
A4: n03 | B4: n04
A5: n04 | B5: n05
A6: n05 | B6: n06
A7: n05 | B7: n07
A8: n05 | B8: n08
A9: n01 | B9: n09
A10: n09 | B10: n10
A11: n10 | B11: n11
A12: n10 | B12: n12
... A123: n01 | B123: n123

Sheet platformNodes
A1: platformID | B1: platform | C1: entity | D1: entityID | E1: webLabel | F1: heatmapLabel | G1: tier1and2entity | H1: tier1and2entityID | I1: website | J1: easeDiscover | K1: methodDiscover | L1: easeAccess | M1: methodAccess | N1: fileFormat | O1: metadata | P1: metadataFormat | Q1: dataDefinitions | R1: metaAttributes | S1: metadataStandards | T1: timeliness | U1: lengthAvailable
A2: p01 | B2: The Water Source | C2: Department of Agriculture | D2: n02 | E2: Ag-Production Ag | F2: =CONCATENATE(E2,": ",B2) -> Ag-Production Ag: The Water Source | G2: =VLOOKUP($D2,orgNodes!$A$2:$D$124,3,FALSE) -> Department of Agriculture | H2: =VLOOKUP($D2,orgNodes!$A$2:$D$124,4,FALSE) -> 2 | I2: http://www.texasagriculture.gov/Home/ProductionAgriculture/TheWaterSource.aspx | J2: Low | K2: Website | L2: Yes | M2: Link to Source | N2: html; csv | O2: No | P2: No | Q2: No | R2: No | S2: No | T2: Irregular | U2: Period of Record
A3: p02 | B3: Studies of Priority Groundwater Management Areas | C3: Water Quantity | D3: n06 | E3: TPWD-Water Quantity | F3: =CONCATENATE(E3,": ",B3) -> TPWD-Water Quantity: Studies of Priority Groundwater Management Areas | G3: =VLOOKUP($D3,orgNodes!$A$2:$D$124,3,FALSE) -> Department of Parks and Wildlife | H3: =VLOOKUP($D3,orgNodes!$A$2:$D$124,4,FALSE) -> 3 | I3: https://tpwd.texas.gov/landwater/water/conservation/water_resources/water_quantity/pgma/ | J3: Low | K3: Website | L3: Yes | M3: Individual Export | N3: pdf | O3: No | P3: No | Q3: No | R3: No | S3: No | T3: Irregular | U3: Not Applicable
A4: p03 | B4: Ecologically Significant Streams | C4: Water Quantity | D4: n06 | E4: TPWD-Water Quantity | F4: =CONCATENATE(E4,": ",B4) -> TPWD-Water Quantity: Ecologically Significant Streams | G4: =VLOOKUP($D4,orgNodes!$A$2:$D$124,3,FALSE) -> Department of Parks and Wildlife | H4: =VLOOKUP($D4,orgNodes!$A$2:$D$124,4,FALSE) -> 3 | I4: https://tpwd.texas.gov/landwater/water/conservation/water_resources/water_quantity/sigsegs/ | J4: Low | K4: Website | L4: Yes | M4: Individual Export | N4: pdf | O4: No | P4: No | Q4: Yes | R4: No | S4: No | T4: Irregular | U4: Not Applicable
A5: p04 | B5: Water Quality Related Reports | C5: Water Quality | D5: n07 | E5: TPWD-Water Quality | F5: =CONCATENATE(E5,": ",B5) -> TPWD-Water Quality: Water Quality Related Reports | G5: =VLOOKUP($D5,orgNodes!$A$2:$D$124,3,FALSE) -> Department of Parks and Wildlife | H5: =VLOOKUP($D5,orgNodes!$A$2:$D$124,4,FALSE) -> 3 | I5: https://tpwd.texas.gov/landwater/water/environconcerns/water_quality/wq_research/WQ_Reports.phtml | J5: Low | K5: Website | L5: Yes | M5: Individual Export | N5: pdf | O5: Yes | P5: pdf | Q5: Yes | R5: Administrative | S5: No | T5: Irregular | U5: Not Applicable
A6: p05 | B6: Reports on River Studies | C6: River Studies | D6: n08 | E6: TPWD-River Studies | F6: =CONCATENATE(E6,": ",B6) -> TPWD-River Studies: Reports on River Studies | G6: =VLOOKUP($D6,orgNodes!$A$2:$D$124,3,FALSE) -> Department of Parks and Wildlife | H6: =VLOOKUP($D6,orgNodes!$A$2:$D$124,4,FALSE) -> 3 | I6: https://tpwd.texas.gov/landwater/water/conservation/fwresources/reports.phtml | J6: Low | K6: Website | L6: Yes | M6: Individual Export | N6: pdf | O6: Yes | P6: pdf | Q6: Yes | R6: Administrative; Descriptive | S6: No | T6: Unknown | U6: Not Applicable
A7: p06 | B7: Drinking Water | C7: Water Supply | D7: n19 | E7: TCEQ-Water Supply | F7: =CONCATENATE(E7,": ",B7) -> TCEQ-Water Supply: Drinking Water | G7: =VLOOKUP($D7,orgNodes!$A$2:$D$124,3,FALSE) -> Texas Commission on Environmental Quality | H7: =VLOOKUP($D7,orgNodes!$A$2:$D$124,4,FALSE) -> 4 | I7: https://www.tceq.texas.gov/drinkingwater | J7: Low | K7: Website | L7: Yes | M7: Individual Export | N7: pdf | O7: Yes | P7: pdf | Q7: Yes | R7: Administrative; Descriptive | S7: No | T7: Yearly or Higher | U7: Not Applicable
A8: p07 | B8: Drinking Water Watch | C8: Water Quality Planning | D8: n13 | E8: TCEQ-Water Quality Planning | F8: =CONCATENATE(E8,": ",B8) -> TCEQ-Water Quality Planning: Drinking Water Watch | G8: =VLOOKUP($D8,orgNodes!$A$2:$D$124,3,FALSE) -> Texas Commission on Environmental Quality | H8: =VLOOKUP($D8,orgNodes!$A$2:$D$124,4,FALSE) -> 4 | I8: http://dww2.tceq.texas.gov/DWW/ | J8: Low | K8: Website | L8: Yes | M8: Copy and Paste | N8: html | O8: No | P8: No | Q8: No | R8: No | S8: No | T8: Irregular | U8: Limited Record
A9: p08 | B9: Water Rights and Water Use Data | C9: Water Availability | D9: n11 | E9: TCEQ-Water Availability | F9: =CONCATENATE(E9,": ",B9) -> TCEQ-Water Availability: Water Rights and Water Use Data | G9: =VLOOKUP($D9,orgNodes!$A$2:$D$124,3,FALSE) -> Texas Commission on Environmental Quality | H9: =VLOOKUP($D9,orgNodes!$A$2:$D$124,4,FALSE) -> 4 | I9: https://www.tceq.texas.gov/permitting/water_rights/wr-permitting/wrwud | J9: Low | K9: Website | L9: Yes | M9: Individual Export | N9: excel; zip | O9: Yes | P9: pdf | Q9: Yes | R9: Administrative; Descriptive | S9: No | T9: Yearly or Higher | U9: Period of Record
A10: p09 | B10: Water Availability Models | C10: Water Availability | D10: n11 | E10: TCEQ-Water Availability | F10: =CONCATENATE(E10,": ",B10) -> TCEQ-Water Availability: Water Availability Models | G10: =VLOOKUP($D10,orgNodes!$A$2:$D$124,3,FALSE) -> Texas Commission on Environmental Quality | H10: =VLOOKUP($D10,orgNodes!$A$2:$D$124,4,FALSE) -> 4 | I10: https://www.tceq.texas.gov/permitting/water_rights/wr_technical-resources/wam.html | J10: Low | K10: Website | L10: Software Required | M10: Individual Export | N10: shapefile; software specific | O10: Yes | P10: pdf | Q10: Yes | R10: Administrative | S10: No | T10: Unknown | U10: Not Applicable
A11: p10 | B11: Texas Integrated Report of Surface Water Quality | C11: Water Quality Standards Program | D11: n14 | E11: TCEQ-Water Quality Standards | F11: =CONCATENATE(E11,": ",B11) -> TCEQ-Water Quality Standards: Texas Integrated Report of Surface Water Quality | G11: =VLOOKUP($D11,orgNodes!$A$2:$D$124,3,FALSE) -> Texas Commission on Environmental Quality | H11: =VLOOKUP($D11,orgNodes!$A$2:$D$124,4,FALSE) -> 4 | I11: https://www.tceq.texas.gov/waterquality/assessment/305_303.html | J11: Low | K11: Website | L11: Yes | M11: Individual Export | N11: pdf | O11: Yes | P11: pdf | Q11: Yes | R11: Administrative | S11: No | T11: Irregular | U11: Period of Record
A12: p11 | B12: Segments with TMDLS | C12: Total Daily Maximum Load Program | D12: n15 | E12: TCEQ-TMDL | F12: =CONCATENATE(E12,": ",B12) -> TCEQ-TMDL: Segments with TMDLS | G12: =VLOOKUP($D12,orgNodes!$A$2:$D$124,3,FALSE) -> Texas Commission on Environmental Quality | H12: =VLOOKUP($D12,orgNodes!$A$2:$D$124,4,FALSE) -> 4 | I12: https://www.tceq.texas.gov/waterquality/tmdl/nav/tmdlsegments | J12: Low | K12: Website | L12: Yes | M12: Copy and Paste | N12: html | O12: No | P12: No | Q12: No | R12: No | S12: No | T12: Unknown | U12: Not Applicable
A13: p12 | B13: Watershed Protection Plans for Nonpoint Source Water Pollution | C13: Nonpoint Source Pollution Program | D13: n16 | E13: TCEQ-Nonpoint Source Pollution | F13: =CONCATENATE(E13,": ",B13) -> TCEQ-Nonpoint Source Pollution: Watershed Protection Plans for Nonpoint Source Water Pollution | G13: =VLOOKUP($D13,orgNodes!$A$2:$D$124,3,FALSE) -> Texas Commission on Environmental Quality | H13: =VLOOKUP($D13,orgNodes!$A$2:$D$124,4,FALSE) -> 4 | I13: https://www.tceq.texas.gov/waterquality/nonpoint-source/mgmt-plan/watershed-pp.html#map | J13: Low | K13: Website | L13: Yes | M13: Link to Source | N13: pdf | O13: No | P13: No | Q13: No | R13: No | S13: No | T13: Monthly or Higher | U13: Not Applicable
... A98: p97 | B98: Purchase Data | C98: Commission on Environmental Quality | D98: n09 | E98: TCEQ-Record Services | F98: =CONCATENATE(E98,": ",B98) -> TCEQ-Record Services: Purchase Data | G98: =VLOOKUP($D98,orgNodes!$A$2:$D$124,3,FALSE) -> Texas Commission on Environmental Quality | H98: =VLOOKUP($D98,orgNodes!$A$2:$D$124,4,FALSE) -> 4 | I98: https://www.tceq.texas.gov/agency/data/records-services/purchase-data.html | J98: Low | K98: Website | L98: Permission Required | M98: None | N98: Unknown | O98: Unknown | P98: Unknown | Q98: Unknown | R98: Unknown | S98: Unknown | T98: Unknown | U98: Unknown

Sheet dataNodes
A1: dataID | B1: dataGroup | C1: dataCategory
A2: d01 | B2: Built | C2: Infrastructure
A3: d02 | B3: Natural | C3: Infrastructure
A4: d03 | B4: Quality | C4: Quality
A5: d04 | B5: Regulatory | C5: Quality
A6: d05 | B6: Evapotranspiration | C6: Quantity
A7: d06 | B7: Extreme Events | C7: Quantity
A8: d07 | B8: Glacial and Snow | C8: Quantity
A9: d08 | B9: Groundwater | C9: Quantity
A10: d09 | B10: Meteorology | C10: Quantity
A11: d10 | B11: Precipitation | C11: Quantity
A12: d11 | B12: Reservoir | C12: Quantity
... A19: d18 | B19: Management Plans | C19: Use

Sheet dataNodeTypes
A1: platformID | B1: platform | C1: entity | D1: tier1and2entity | E1: website | F1: data | G1: dataGroup | H1: dataCategory | I1: dataID | J1: notes | M1: dataGroup - linked to dataNodes tab | N1: dataID - linked to dataNodes tab
A2: p01 | B2: The Water Source | C2: Production Agriculture | D2: Department of Agriculture | E2: http://www.texasagriculture.gov/Home/ProductionAgriculture/TheWaterSource.aspx | F2: Reservoir Levels | G2: Reservoir | H2: =VLOOKUP(G2,dataNodes!$B$2:$C$19,2,FALSE) -> Quantity | I2: =VLOOKUP(G2,$M$2:$N$19,2,FALSE) -> d11 | M2: =dataNodes!B2 -> Built | N2: =dataNodes!A2 -> d01
A3: p01 | B3: The Water Source | C3: Production Agriculture | D3: Department of Agriculture | E3: http://www.texasagriculture.gov/Home/ProductionAgriculture/TheWaterSource.aspx | F3: Drought Monitor | G3: Extreme Events | H3: =VLOOKUP(G3,dataNodes!$B$2:$C$19,2,FALSE) -> Quantity | I3: =VLOOKUP(G3,$M$2:$N$19,2,FALSE) -> d06 | M3: =dataNodes!B3 -> Natural | N3: =dataNodes!A3 -> d02
A4: p02 | B4: Studies of Priority Groundwater Management Areas | C4: Water Quantity | D4: Department of Parks and Wildlife | E4: https://tpwd.texas.gov/landwater/water/conservation/water_resources/water_quantity/pgma/ | F4: Groundwater Management Areas | G4: Management Plans | H4: =VLOOKUP(G4,dataNodes!$B$2:$C$19,2,FALSE) -> Use | I4: =VLOOKUP(G4,$M$2:$N$19,2,FALSE) -> d18 | M4: =dataNodes!B4 -> Quality | N4: =dataNodes!A4 -> d03
A5: p03 | B5: Ecologically Significant Streams | C5: Water Quantity | D5: Department of Parks and Wildlife | E5: https://tpwd.texas.gov/landwater/water/conservation/water_resources/water_quantity/sigsegs/ | F5: Significant Stream Segments | G5: Management Plans | H5: =VLOOKUP(G5,dataNodes!$B$2:$C$19,2,FALSE) -> Use | I5: =VLOOKUP(G5,$M$2:$N$19,2,FALSE) -> d18 | M5: =dataNodes!B5 -> Regulatory | N5: =dataNodes!A5 -> d04
A6: p04 | B6: Water Quality Related Reports | C6: Water Quality | D6: Department of Parks and Wildlife | E6: https://tpwd.texas.gov/landwater/water/environconcerns/water_quality/wq_research/WQ_Reports.phtml | F6: Water Quality Related Reports | G6: Quality | H6: =VLOOKUP(G6,dataNodes!$B$2:$C$19,2,FALSE) -> Quality | I6: =VLOOKUP(G6,$M$2:$N$19,2,FALSE) -> d03 | M6: =dataNodes!B6 -> Evapotranspiration | N6: =dataNodes!A6 -> d05
A7: p05 | B7: Reports on River Studies | C7: River Studies | D7: Department of Parks and Wildlife | E7: https://tpwd.texas.gov/landwater/water/conservation/fwresources/reports.phtml | F7: Biological Assessments | G7: Quality | H7: =VLOOKUP(G7,dataNodes!$B$2:$C$19,2,FALSE) -> Quality | I7: =VLOOKUP(G7,$M$2:$N$19,2,FALSE) -> d03 | M7: =dataNodes!B7 -> Extreme Events | N7: =dataNodes!A7 -> d06
A8: p06 | B8: Drinking Water | C8: Water Supply | D8: Commission on Environmental Quality | E8: https://www.tceq.texas.gov/drinkingwater | F8: Public System Compliance Report | G8: Utilities | H8: =VLOOKUP(G8,dataNodes!$B$2:$C$19,2,FALSE) -> Use | I8: =VLOOKUP(G8,$M$2:$N$19,2,FALSE) -> d17 | J8: TX Utilities | M8: =dataNodes!B8 -> Glacial and Snow | N8: =dataNodes!A8 -> d07
A9: p07 | B9: Drinking Water Watch | C9: Water Quality Planning | D9: Commission on Environmental Quality | E9: http://dww2.tceq.texas.gov/DWW/ | F9: Daily Demand; Daily Usage; Capacity; | G9: Utilities | H9: =VLOOKUP(G9,dataNodes!$B$2:$C$19,2,FALSE) -> Use | I9: =VLOOKUP(G9,$M$2:$N$19,2,FALSE) -> d17 | J9: Has quantity, quality, and use data. Keep as Use for Utility. May rethink later. | M9: =dataNodes!B9 -> Groundwater | N9: =dataNodes!A9 -> d08
A10: p08 | B10: Water Rights and Water Use Data | C10: Water Availability | D10: Commission on Environmental Quality | E10: https://www.tceq.texas.gov/permitting/water_rights/wr-permitting/wrwud | F10: Water Rights | G10: Use | H10: =VLOOKUP(G10,dataNodes!$B$2:$C$19,2,FALSE) -> Use | I10: =VLOOKUP(G10,$M$2:$N$19,2,FALSE) -> d16 | M10: =dataNodes!B10 -> Meteorology | N10: =dataNodes!A10 -> d09
A11: p08 | B11: Water Rights and Water Use Data | C11: Water Availability | D11: Commission on Environmental Quality | E11: https://www.tceq.texas.gov/permitting/water_rights/wr-permitting/wrwud | F11: Diversion Locations | G11: Built | H11: =VLOOKUP(G11,dataNodes!$B$2:$C$19,2,FALSE) -> Infrastructure | I11: =VLOOKUP(G11,$M$2:$N$19,2,FALSE) -> d01 | M11: =dataNodes!B11 -> Precipitation | N11: =dataNodes!A11 -> d10
A12: p09 | B12: Water Availability Models | C12: Water Availability | D12: Commission on Environmental Quality | E12: https://www.tceq.texas.gov/permitting/water_rights/wr_technical-resources/wam.html | F12: Diversion points and control points | G12: Built | H12: =VLOOKUP(G12,dataNodes!$B$2:$C$19,2,FALSE) -> Infrastructure | I12: =VLOOKUP(G12,$M$2:$N$19,2,FALSE) -> d01 | M12: =dataNodes!B12 -> Reservoir | N12: =dataNodes!A12 -> d11
A13: p09 | B13: Water Availability Models | C13: Water Availability | D13: Commission on Environmental Quality | E13: https://www.tceq.texas.gov/permitting/water_rights/wr_technical-resources/wam.html | F13: Flowlines | G13: Natural | H13: =VLOOKUP(G13,dataNodes!$B$2:$C$19,2,FALSE) -> Infrastructure | I13: =VLOOKUP(G13,$M$2:$N$19,2,FALSE) -> d02 | M13: =dataNodes!B13 -> Soil | N13: =dataNodes!A13 -> d12
A14: p09 | B14: Water Availability Models | C14: Water Availability | D14: Commission on Environmental Quality | E14: https://www.tceq.texas.gov/permitting/water_rights/wr_technical-resources/wam.html | F14: Streamflow | G14: Surface Water | H14: =VLOOKUP(G14,dataNodes!$B$2:$C$19,2,FALSE) -> Quantity | I14: =VLOOKUP(G14,$M$2:$N$19,2,FALSE) -> d13 | M14: =dataNodes!B14 -> Surface Water | N14: =dataNodes!A14 -> d13
A15: p09 | B15: Water Availability Models | C15: Water Availability | D15: Commission on Environmental Quality | E15: https://www.tceq.texas.gov/permitting/water_rights/wr_technical-resources/wam.html | F15: Return Flow | G15: Use | H15: =VLOOKUP(G15,dataNodes!$B$2:$C$19,2,FALSE) -> Use | I15: =VLOOKUP(G15,$M$2:$N$19,2,FALSE) -> d16 | M15: =dataNodes!B15 -> Hydropower | N15: =dataNodes!A15 -> d14
A16: p10 | B16: Texas Integrated Report of Surface Water Quality | C16: Water Quality Standards Program | D16: Commission on Environmental Quality | E16: https://www.tceq.texas.gov/waterquality/assessment/305_303.html | F16: 303d List | G16: Quality | H16: =VLOOKUP(G16,dataNodes!$B$2:$C$19,2,FALSE) -> Quality | I16: =VLOOKUP(G16,$M$2:$N$19,2,FALSE) -> d03 | M16: =dataNodes!B16 -> Irrigation | N16: =dataNodes!A16 -> d15
A17: p10 | B17: Texas Integrated Report of Surface Water Quality | C17: Water Quality Standards Program | D17: Commission on Environmental Quality | E17: https://www.tceq.texas.gov/waterquality/assessment/305_303.html | F17: Surface Water Quality Standards | G17: Regulatory | H17: =VLOOKUP(G17,dataNodes!$B$2:$C$19,2,FALSE) -> Quality | I17: =VLOOKUP(G17,$M$2:$N$19,2,FALSE) -> d04 | M17: =dataNodes!B17 -> Use | N17: =dataNodes!A17 -> d16
A18: p11 | B18: Segments with TMDLS | C18: Total Daily Maximum Load Program | D18: Commission on Environmental Quality | E18: https://www.tceq.texas.gov/waterquality/tmdl/nav/tmdlsegments | F18: Stream segments with TMDLS | G18: Quality | H18: =VLOOKUP(G18,dataNodes!$B$2:$C$19,2,FALSE) -> Quality | I18: =VLOOKUP(G18,$M$2:$N$19,2,FALSE) -> d03 | M18: =dataNodes!B18 -> Utilities | N18: =dataNodes!A18 -> d17
A19: p12 | B19: Watershed Protection Plans for Nonpoint Source Water Pollution | C19: Nonpoint Source Pollution Program | D19: Commission on Environmental Quality | E19: https://www.tceq.texas.gov/waterquality/nonpoint-source/mgmt-plan/watershed-pp.html#map | F19: protection plans | G19: Management Plans | H19: =VLOOKUP(G19,dataNodes!$B$2:$C$19,2,FALSE) -> Use | I19: =VLOOKUP(G19,$M$2:$N$19,2,FALSE) -> d18 | M19: =dataNodes!B19 -> Management Plans | N19: =dataNodes!A19 -> d18
A20: p13 | B20: Continuous Water Quality Monitoring Network | C20: Surface Water Quality Monitoring Program | D20: Commission on Environmental Quality | E20: https://www.tceq.texas.gov/waterquality/monitoring/swqm_realtime.html | F20: Streamflow | G20: Surface Water | H20: =VLOOKUP(G20,dataNodes!$B$2:$C$19,2,FALSE) -> Quantity | I20: =VLOOKUP(G20,$M$2:$N$19,2,FALSE) -> d13
A21: p13 | B21: Continuous Water Quality Monitoring Network | C21: Surface Water Quality Monitoring Program | D21: Commission on Environmental Quality | E21: https://www.tceq.texas.gov/waterquality/monitoring/swqm_realtime.html | F21: DO, SC, Temperature | G21: Quality | H21: =VLOOKUP(G21,dataNodes!$B$2:$C$19,2,FALSE) -> Quality | I21: =VLOOKUP(G21,$M$2:$N$19,2,FALSE) -> d03
A22: p14 | B22: Groundwater Contamination Viewer | C22: Water Availability | D22: Commission on Environmental Quality | E22: http://tceq.maps.arcgis.com/apps/webappviewer/index.html?id=478b575733ca4662a1441f93c9b973f5 | F22: Contamination descriptions | G22: Regulatory | H22: =VLOOKUP(G22,dataNodes!$B$2:$C$19,2,FALSE) -> Quality | I22: =VLOOKUP(G22,$M$2:$N$19,2,FALSE) -> d04
A23: p15 | B23: Pesticides and Groundwater | C23: Water Availability | D23: Commission on Environmental Quality | E23: https://www.tceq.texas.gov/groundwater/pesticides.html | F23: Pesticide groundater monitoring data | G23: Quality | H23: =VLOOKUP(G23,dataNodes!$B$2:$C$19,2,FALSE) -> Quality | I23: =VLOOKUP(G23,$M$2:$N$19,2,FALSE) -> d03
A24: p15 | B24: Pesticides and Groundwater | C24: Water Availability | D24: Commission on Environmental Quality | E24: https://www.tceq.texas.gov/groundwater/pesticides.html | F24: Management plan to prvent groundwater contamination by pesticides | G24: Management Plans | H24: =VLOOKUP(G24,dataNodes!$B$2:$C$19,2,FALSE) -> Use | I24: =VLOOKUP(G24,$M$2:$N$19,2,FALSE) -> d18
A25: p16 | B25: List of Texas PWSs Limiting Water Use to Avoid Shortages | C25: Water Supply | D25: Commission on Environmental Quality | E25: https://www.tceq.texas.gov/drinkingwater/trot/droughtw.html | F25: Public Water Supplies with Drought Restrictions | G25: Utilities | H25: =VLOOKUP(G25,dataNodes!$B$2:$C$19,2,FALSE) -> Use | I25: =VLOOKUP(G25,$M$2:$N$19,2,FALSE) -> d17 | J25: TX Utilities
A26: p16 | B26: List of Texas PWSs Limiting Water Use to Avoid Shortages | C26: Water Supply | D26: Commission on Environmental Quality | E26: https://www.tceq.texas.gov/response/drought | F26: Drought information | G26: Extreme Events | H26: =VLOOKUP(G26,dataNodes!$B$2:$C$19,2,FALSE) -> Quantity | I26: =VLOOKUP(G26,$M$2:$N$19,2,FALSE) -> d06
A27: p17 | B27: Geographic Information Systems | C27: Water | D27: Commission on Environmental Quality | E27: https://www.tceq.texas.gov/gis/download-tceq-gis-data#waterdatasets | F27: Water districts, groundwater conservation districts, management areas, TCEQ regions, monitoring stations, well locations, water supply intakes | G27: Built | H27: =VLOOKUP(G27,dataNodes!$B$2:$C$19,2,FALSE) -> Infrastructure | I27: =VLOOKUP(G27,$M$2:$N$19,2,FALSE) -> d01 | J27: TX Utilities
A28: p17 | B28: Geographic Information Systems | C28: Water | D28: Commission on Environmental Quality | E28: https://www.tceq.texas.gov/gis/download-tceq-gis-data#waterdatasets | F28: flowlines, aquifer boundaries | G28: Natural | H28: =VLOOKUP(G28,dataNodes!$B$2:$C$19,2,FALSE) -> Infrastructure | I28: =VLOOKUP(G28,$M$2:$N$19,2,FALSE) -> d02
A29: p18 | B29: Compliance History Database | C29: Water Supply | D29: Commission on Environmental Quality | E29: http://www2.tceq.texas.gov/oce/ch/index.cfm | F29: Not sure | G29: Regulatory | H29: =VLOOKUP(G29,dataNodes!$B$2:$C$19,2,FALSE) -> Quality | I29: =VLOOKUP(G29,$M$2:$N$19,2,FALSE) -> d04
A30: p19 | B30: Surface Water Quality Monitoring Information System | C30: Surface Water Quality Monitoring Program | D30: Commission on Environmental Quality | E30: https://www80.tceq.texas.gov/SwqmisWeb/ | F30: Surface Water Quality Standards | G30: Quality | H30: =VLOOKUP(G30,dataNodes!$B$2:$C$19,2,FALSE) -> Quality | I30: =VLOOKUP(G30,$M$2:$N$19,2,FALSE) -> d03
A31: p20 | B31: State of Texas Environmental Electronic Reporting System | C31: Environmental Electronic Reporting System | D31: Commission on Environmental Quality | E31: https://www3.tceq.texas.gov/steers/ | F31: Permits | G31: Regulatory | H31: =VLOOKUP(G31,dataNodes!$B$2:$C$19,2,FALSE) -> Quality | I31: =VLOOKUP(G31,$M$2:$N$19,2,FALSE) -> d04 | J31: Might have other regulatory requirements but not sure.
A32: p21 | B32: Status of Stormwater and Wastewater Applications and Specifications | C32: Water Quality | D32: Commission on Environmental Quality | E32: https://www.tceq.texas.gov/agency/data/lookup-data/status-stormwater-wastewater.html | F32: Status of permits | G32: Regulatory | H32: =VLOOKUP(G32,dataNodes!$B$2:$C$19,2,FALSE) -> Quality | I32: =VLOOKUP(G32,$M$2:$N$19,2,FALSE) -> d04
A33: p21 | B33: Status of Stormwater and Wastewater Applications and Specifications | C33: Water Quality | D33: Commission on Environmental Quality | E33: https://www.tceq.texas.gov/agency/data/lookup-data/status-stormwater-wastewater.html | F33: Status of stormwater and wastewater permits | G33: Use | H33: =VLOOKUP(G33,dataNodes!$B$2:$C$19,2,FALSE) -> Use | I33: =VLOOKUP(G33,$M$2:$N$19,2,FALSE) -> d16 | J33: I'm not sure if this is regulatory or utility
A34: p22 | B34: CRP Data Tool | C34: Clean Rivers Program | D34: Commission on Environmental Quality | E34: https://www80.tceq.texas.gov/SwqmisWeb/public/crpweb.faces | F34: Location and status of monitoring stations | G34: Built | H34: =VLOOKUP(G34,dataNodes!$B$2:$C$19,2,FALSE) -> Infrastructure | I34: =VLOOKUP(G34,$M$2:$N$19,2,FALSE) -> d01
A35: p22 | B35: CRP Data Tool | C35: Clean Rivers Program | D35: Commission on Environmental Quality | E35: https://www80.tceq.texas.gov/SwqmisWeb/public/crpweb.faces | F35: Water Quality parameters | G35: Quality | H35: =VLOOKUP(G35,dataNodes!$B$2:$C$19,2,FALSE) -> Quality | I35: =VLOOKUP(G35,$M$2:$N$19,2,FALSE) -> d03
A36: p23 | B36: Water District Database | C36: Water Supply | D36: Commission on Environmental Quality | E36: http://www14.tceq.texas.gov/iwud/ | F36: Maps of service areas | G36: Built | H36: =VLOOKUP(G36,dataNodes!$B$2:$C$19,2,FALSE) -> Infrastructure | I36: =VLOOKUP(G36,$M$2:$N$19,2,FALSE) -> d01
A37: p23 | B37: Water District Database | C37: Water Supply | D37: Commission on Environmental Quality | E37: http://www14.tceq.texas.gov/iwud/ | F37: Water Districts Data | G37: Use | H37: =VLOOKUP(G37,dataNodes!$B$2:$C$19,2,FALSE) -> Use | I37: =VLOOKUP(G37,$M$2:$N$19,2,FALSE) -> d16 | J37: Unknown - cannot access
A38: p24 | B38: Water Data for Texas | C38: Texas Water Development Board | D38: Texas Water Development Board | E38: https://waterdatafortexas.org/reservoirs/statewide | F38: Reservoir Levels | G38: Reservoir | H38: =VLOOKUP(G38,dataNodes!$B$2:$C$19,2,FALSE) -> Quantity | I38: =VLOOKUP(G38,$M$2:$N$19,2,FALSE) -> d11
A39: p24 | B39: Water Data for Texas | C39: Texas Water Development Board | D39: Texas Water Development Board | E39: https://waterdatafortexas.org/reservoirs/statewide | F39: Station locations, reservoir locations | G39: Built | H39: =VLOOKUP(G39,dataNodes!$B$2:$C$19,2,FALSE) -> Infrastructure | I39: =VLOOKUP(G39,$M$2:$N$19,2,FALSE) -> d01
A40: p24 | B40: Water Data for Texas | C40: Texas Water Development Board | D40: Texas Water Development Board | E40: https://waterdatafortexas.org/reservoirs/statewide | F40: Rainfall Forecasts | G40: Precipitation | H40: =VLOOKUP(G40,dataNodes!$B$2:$C$19,2,FALSE) -> Quantity | I40: =VLOOKUP(G40,$M$2:$N$19,2,FALSE) -> d10
A41: p24 | B41: Water Data for Texas | C41: Texas Water Development Board | D41: Texas Water Development Board | E41: https://waterdatafortexas.org/reservoirs/statewide | F41: Evaporation Forecasts | G41: Evapotranspiration | H41: =VLOOKUP(G41,dataNodes!$B$2:$C$19,2,FALSE) -> Quantity | I41: =VLOOKUP(G41,$M$2:$N$19,2,FALSE) -> d05
A42: p24 | B42: Water Data for Texas | C42: Texas Water Development Board | D42: Texas Water Development Board | E42: https://waterdatafortexas.org/reservoirs/statewide | F42: Drought Indices; Reservoirs in Flood Stage | G42: Extreme Events | H42: =VLOOKUP(G42,dataNodes!$B$2:$C$19,2,FALSE) -> Quantity | I42: =VLOOKUP(G42,$M$2:$N$19,2,FALSE) -> d06
A43: p24 | B43: Water Data for Texas | C43: Texas Water Development Board | D43: Texas Water Development Board | E43: https://waterdatafortexas.org/reservoirs/statewide | F43: Groundwater Levels | G43: Groundwater | H43: =VLOOKUP(G43,dataNodes!$B$2:$C$19,2,FALSE) -> Quantity | I43: =VLOOKUP(G43,$M$2:$N$19,2,FALSE) -> d08
A44: p24 | B44: Water Data for Texas | C44: Texas Water Development Board | D44: Texas Water Development Board | E44: https://waterdatafortexas.org/reservoirs/statewide | F44: Water quality monitoring | G44: Quality | H44: =VLOOKUP(G44,dataNodes!$B$2:$C$19,2,FALSE) -> Quality | I44: =VLOOKUP(G44,$M$2:$N$19,2,FALSE) -> d03
A45: p25 | B45: Groundwater Database | C45: Groundwater Monitoring | D45: Texas Water Development Board | E45: http://www.twdb.texas.gov/groundwater/data/gwdbrpt.asp | F45: Groundwater Levels, aquifer levels, groundwater availability models | G45: Groundwater | H45: =VLOOKUP(G45,dataNodes!$B$2:$C$19,2,FALSE) -> Quantity | I45: =VLOOKUP(G45,$M$2:$N$19,2,FALSE) -> d08
A46: p25 | B46: Groundwater Database | C46: Groundwater Monitoring | D46: Texas Water Development Board | E46: http://www.twdb.texas.gov/groundwater/data/gwdbrpt.asp | F46: Groundwater Levels, aquifer levels | G46: Management Plans | H46: =VLOOKUP(G46,dataNodes!$B$2:$C$19,2,FALSE) -> Use | I46: =VLOOKUP(G46,$M$2:$N$19,2,FALSE) -> d18
A47: p26 | B47: GIS Data | C47: Texas Water Development Board | D47: Texas Water Development Board | E47: http://www.twdb.texas.gov/mapping/gisdata.asp | F47: Natural Features - aquifers, river basins, etc. | G47: Natural | H47: =VLOOKUP(G47,dataNodes!$B$2:$C$19,2,FALSE) -> Infrastructure | I47: =VLOOKUP(G47,$M$2:$N$19,2,FALSE) -> d02
A48: p26 | B48: GIS Data | C48: Texas Water Development Board | D48: Texas Water Development Board | E48: http://www.twdb.texas.gov/mapping/gisdata.asp | F48: Administrative Boundaries | G48: Built | H48: =VLOOKUP(G48,dataNodes!$B$2:$C$19,2,FALSE) -> Infrastructure | I48: =VLOOKUP(G48,$M$2:$N$19,2,FALSE) -> d01
A49: p27 | B49: TexMesonet | C49: TexMesonet and Hydrosurvey | D49: Texas Water Development Board | E49: https://www.texmesonet.org/ | F49: Precipitation | G49: Precipitation | H49: =VLOOKUP(G49,dataNodes!$B$2:$C$19,2,FALSE) -> Quantity | I49: =VLOOKUP(G49,$M$2:$N$19,2,FALSE) -> d10
... A63: p31 | B63: Regional Water Planning Data | C63: Regional Water Planning | D63: Texas Water Development Board | E63: http://www.twdb.texas.gov/waterplanning/data/rwp-database/index.asp | F63: State water plans | G63: Management Plans | H63: =VLOOKUP(G63,dataNodes!$B$2:$C$19,2,FALSE) -> Use | I63: =VLOOKUP(G63,$M$2:$N$19,2,FALSE) -> d18
A64: p31 | B64: Regional Water Planning Data | C64: Regional Water Planning | D64: Texas Water Development Board | E64: http://www.twdb.texas.gov/waterplanning/data/rwp-database/index.asp | F64: Water use data by category, population, projections | G64: Use | H64: =VLOOKUP(G64,dataNodes!$B$2:$C$19,2,FALSE) -> Use | I64: =VLOOKUP(G64,$M$2:$N$19,2,FALSE) -> d16 | J64: VERY COOL - CAN GET DATA FROM API - CLICK ON ABOUT
A65: p32 | B65: Historical Water Use Estimates | C65: Water Use | D65: Texas Water Development Board | E65: http://www.twdb.texas.gov/waterplanning/waterusesurvey/estimates/index.asp | F65: Water use by planning region, county, river basin, etc. and sector | G65: Use | H65: =VLOOKUP(G65,dataNodes!$B$2:$C$19,2,FALSE) -> Use | I65: =VLOOKUP(G65,$M$2:$N$19,2,FALSE) -> d16
A66: p32 | B66: Historical Water Use Estimates | C66: Water Use | D66: Texas Water Development Board | E66: http://www.twdb.texas.gov/waterplanning/waterusesurvey/estimates/index.asp | F66: Detailed water use for 2016 | G66: Utilities | H66: =VLOOKUP(G66,dataNodes!$B$2:$C$19,2,FALSE) -> Use | I66: =VLOOKUP(G66,$M$2:$N$19,2,FALSE) -> d17
A67: p33 | B67: Submitted Drillers Reports Database | C67: Groundwater Monitoring | D67: Texas Water Development Board | E67: http://www.twdb.texas.gov/groundwater/data/drillersdb.asp | F67: Location and type of well being drilled | G67: Built | H67: =VLOOKUP(G67,dataNodes!$B$2:$C$19,2,FALSE) -> Infrastructure | I67: =VLOOKUP(G67,$M$2:$N$19,2,FALSE) -> d01
A68: p34 | B68: Texas Water Conditions Report | C68: WAM | D68: Texas Water Development Board | E68: http://www.twdb.texas.gov/surfacewater/conditions/report/index.asp | F68: Precipitation | G68: Precipitation | H68: =VLOOKUP(G68,dataNodes!$B$2:$C$19,2,FALSE) -> Quantity | I68: =VLOOKUP(G68,$M$2:$N$19,2,FALSE) -> d10
A69: p34 | B69: Texas Water Conditions Report | C69: WAM | D69: Texas Water Development Board | E69: http://www.twdb.texas.gov/surfacewater/conditions/report/index.asp | F69: Reservoir Levels | G69: Reservoir | H69: =VLOOKUP(G69,dataNodes!$B$2:$C$19,2,FALSE) -> Quantity | I69: =VLOOKUP(G69,$M$2:$N$19,2,FALSE) -> d11
A70: p34 | B70: Texas Water Conditions Report | C70: WAM | D70: Texas Water Development Board | E70: http://www.twdb.texas.gov/surfacewater/conditions/report/index.asp | F70: Streamflow | G70: Surface Water | H70: =VLOOKUP(G70,dataNodes!$B$2:$C$19,2,FALSE) -> Quantity | I70: =VLOOKUP(G70,$M$2:$N$19,2,FALSE) -> d13
A71: p34 | B71: Texas Water Conditions Report | C71: WAM | D71: Texas Water Development Board | E71: http://www.twdb.texas.gov/surfacewater/conditions/report/index.asp | F71: Soil moisture | G71: Soil | H71: =VLOOKUP(G71,dataNodes!$B$2:$C$19,2,FALSE) -> Quantity | I71: =VLOOKUP(G71,$M$2:$N$19,2,FALSE) -> d12
A72: p34 | B72: Texas Water Conditions Report | C72: WAM | D72: Texas Water Development Board | E72: http://www.twdb.texas.gov/surfacewater/conditions/report/index.asp | F72: Groundwater levels | G72: Groundwater | H72: =VLOOKUP(G72,dataNodes!$B$2:$C$19,2,FALSE) -> Quantity | I72: =VLOOKUP(G72,$M$2:$N$19,2,FALSE) -> d08
A73: p35 | B73: Precipitation and Lake Evaporation | C73: WAM | D73: Texas Water Development Board | E73: http://www.twdb.texas.gov/surfacewater/conditions/evaporation/index.asp | F73: Precipitation | G73: Precipitation | H73: =VLOOKUP(G73,dataNodes!$B$2:$C$19,2,FALSE) -> Quantity | I73: =VLOOKUP(G73,$M$2:$N$19,2,FALSE) -> d10
A74: p35 | B74: Precipitation and Lake Evaporation | C74: WAM | D74: Texas Water Development Board | E74: http://www.twdb.texas.gov/surfacewater/conditions/evaporation/index.asp | F74: Lake Evaporation Data | G74: Reservoir | H74: =VLOOKUP(G74,dataNodes!$B$2:$C$19,2,FALSE) -> Quantity | I74: =VLOOKUP(G74,$M$2:$N$19,2,FALSE) -> d11
A75: p35 | B75: Precipitation and Lake Evaporation | C75: WAM | D75: Texas Water Development Board | E75: http://www.twdb.texas.gov/surfacewater/conditions/evaporation/index.asp | F75: Lake Evaporation Data | G75: Evapotranspiration | H75: =VLOOKUP(G75,dataNodes!$B$2:$C$19,2,FALSE) -> Quantity | I75: =VLOOKUP(G75,$M$2:$N$19,2,FALSE) -> d05
A76: p36 | B76: Lake Surveys | C76: WAM | D76: Texas Water Development Board | E76: http://www.twdb.texas.gov/surfacewater/surveys/completed/index.asp | F76: Contour map, elevation-area-capacity table | G76: Reservoir | H76: =VLOOKUP(G76,dataNodes!$B$2:$C$19,2,FALSE) -> Quantity | I76: =VLOOKUP(G76,$M$2:$N$19,2,FALSE) -> d11
... A85: p40 | B85: Water Reuse | C85: Innovative Water Technologies | D85: Texas Water Development Board | E85: http://www.twdb.texas.gov/innovativewater/reuse/index.asp | F85: Water reuse as a management strategy for small communities | G85: Management Plans | H85: =VLOOKUP(G85,dataNodes!$B$2:$C$19,2,FALSE) -> Use | I85: =VLOOKUP(G85,$M$2:$N$19,2,FALSE) -> d18
A86: p41 | B86: Texas Natural Resources Information System | C86: Texas Natural Resources Information System | D86: Texas Water Development Board | E86: https://tnris.org/ | F86: Floodplain boundaires; low water crossing locations, High water marks inventory | G86: Extreme Events | H86: =VLOOKUP(G86,dataNodes!$B$2:$C$19,2,FALSE) -> Quantity | I86: =VLOOKUP(G86,$M$2:$N$19,2,FALSE) -> d06 | J86: Has munisipal setting designations boundaries
A87: p41 | B87: Texas Natural Resources Information System | C87: Texas Natural Resources Information System | D87: Texas Water Development Board | E87: https://tnris.org/ | F87: River basins; NHD streams and water bodies; Wetlands Inventory | G87: Natural | H87: =VLOOKUP(G87,dataNodes!$B$2:$C$19,2,FALSE) -> Infrastructure | I87: =VLOOKUP(G87,$M$2:$N$19,2,FALSE) -> d02
A88: p41 | B88: Texas Natural Resources Information System | C88: Texas Natural Resources Information System | D88: Texas Water Development Board | E88: https://tnris.org/ | F88: Water Districts, Well Locations; Groundwater Conservation Districts; Edwards Aquifer Regulatory Boundary; Reservoir locations | G88: Built | H88: =VLOOKUP(G88,dataNodes!$B$2:$C$19,2,FALSE) -> Infrastructure | I88: =VLOOKUP(G88,$M$2:$N$19,2,FALSE) -> d01
A89: p41 | B89: Texas Natural Resources Information System | C89: Texas Natural Resources Information System | D89: Texas Water Development Board | E89: https://tnris.org/ | F89: Soil Survey | G89: Soil | H89: =VLOOKUP(G89,dataNodes!$B$2:$C$19,2,FALSE) -> Quantity | I89: =VLOOKUP(G89,$M$2:$N$19,2,FALSE) -> d12
A90: p42 | B90: Water Service Boundary Viewer | C90: Water Use | D90: Texas Water Development Board | E90: https://www2.twdb.texas.gov/apps/waterserviceboundaries | F90: Public Water Supply Boundaries | G90: Built | H90: =VLOOKUP(G90,dataNodes!$B$2:$C$19,2,FALSE) -> Infrastructure | I90: =VLOOKUP(G90,$M$2:$N$19,2,FALSE) -> d01 | J90: TX Utilities
A91: p43 | B91: Flood Control Program | C91: Flood Control Program | D91: Soil and Water Conservation Board | E91: https://www.tsswcb.texas.gov/programs/flood-control-program | F91: List of flood control dams | G91: Built | H91: =VLOOKUP(G91,dataNodes!$B$2:$C$19,2,FALSE) -> Infrastructure | I91: =VLOOKUP(G91,$M$2:$N$19,2,FALSE) -> d01
A92: p44 | B92: Watershed Protection Plans | C92: Nonpoint Source Management Program | D92: Soil and Water Conservation Board | E92: https://www.tsswcb.texas.gov/programs/texas-nonpoint-source-management-program/watershed-protection-plan-program | F92: Reports on water quality improvements | G92: Quality | H92: =VLOOKUP(G92,dataNodes!$B$2:$C$19,2,FALSE) -> Quality | I92: =VLOOKUP(G92,$M$2:$N$19,2,FALSE) -> d03
A93: p44 | B93: Watershed Protection Plans | C93: Nonpoint Source Management Program | D93: Soil and Water Conservation Board | E93: https://www.tsswcb.texas.gov/programs/texas-nonpoint-source-management-program/watershed-protection-plan-program | F93: Watershed protection plans | G93: Management Plans | H93: =VLOOKUP(G93,dataNodes!$B$2:$C$19,2,FALSE) -> Use | I93: =VLOOKUP(G93,$M$2:$N$19,2,FALSE) -> d18
A94: p45 | B94: Agency Reports | C94: Soil and Water Conservation Board | D94: Soil and Water Conservation Board | E94: https://www.tsswcb.texas.gov/about/agency-reports | F94: All kinds of reports: agricultural water conservation, nonpoint source, annual reports, water quality management plan reports | G94: Management Plans | H94: =VLOOKUP(G94,dataNodes!$B$2:$C$19,2,FALSE) -> Use | I94: =VLOOKUP(G94,$M$2:$N$19,2,FALSE) -> d18
A95: p46 | B95: TGCP Publications | C95: Texas Groundwater Protection Committee | D95: Texas Groundwater Protection Committee | E95: http://tgpc.state.tx.us/tgpc-publications/ | F95: All types of reports on groundwater quantity and quality | G95: Management Plans | H95: =VLOOKUP(G95,dataNodes!$B$2:$C$19,2,FALSE) -> Use | I95: =VLOOKUP(G95,$M$2:$N$19,2,FALSE) -> d18
A96: p47 | B96: Texas Open Data Portal | C96: Statewide Data Coordination | D96: Department of Information Resources | E96: https://data.texas.gov/ | F96: Austin water consumptioni | G96: Utilities | H96: =VLOOKUP(G96,dataNodes!$B$2:$C$19,2,FALSE) -> Use | I96: =VLOOKUP(G96,$M$2:$N$19,2,FALSE) -> d17 | J96: Austin Water Utility put up a ton of data if ever we want to do something in-depth
A97: p47 | B97: Texas Open Data Portal | C97: Statewide Data Coordination | D97: Department of Information Resources | E97: https://data.texas.gov/ | F97: Water Quality data | G97: Quality | H97: =VLOOKUP(G97,dataNodes!$B$2:$C$19,2,FALSE) -> Quality | I97: =VLOOKUP(G97,$M$2:$N$19,2,FALSE) -> d03
A98: p47 | B98: Texas Open Data Portal | C98: Statewide Data Coordination | D98: Department of Information Resources | E98: https://data.texas.gov/ | F98: Location of intakes, reservoirs, watershed boundaries, etc | G98: Built | H98: =VLOOKUP(G98,dataNodes!$B$2:$C$19,2,FALSE) -> Infrastructure | I98: =VLOOKUP(G98,$M$2:$N$19,2,FALSE) -> d01
A99: p48 | B99: Consumer Information | C99: Water Delivery | D99: Angelina and Neches River Authority | E99: https://www.anra.org/divisions/water_delivery/holmwood_utilities/consumer_information.html | F99: Consumer Confidence Reports | G99: Regulatory | H99: =VLOOKUP(G99,dataNodes!$B$2:$C$19,2,FALSE) -> Quality | I99: =VLOOKUP(G99,$M$2:$N$19,2,FALSE) -> d04
A100: p48 | B100: Consumer Information | C100: Water Delivery | D100: Angelina and Neches River Authority | E100: https://www.anra.org/divisions/water_delivery/holmwood_utilities/consumer_information.html | F100: Consumer Confidence Reports | G100: Utilities | H100: =VLOOKUP(G100,dataNodes!$B$2:$C$19,2,FALSE) -> Use | I100: =VLOOKUP(G100,$M$2:$N$19,2,FALSE) -> d17
A101: p49 | B101: Drought Information | C101: Reservoirs | D101: Angelina and Neches River Authority | E101: https://www.anra.org/resources/drought_information.html | F101: Drought data | G101: Extreme Events | H101: =VLOOKUP(G101,dataNodes!$B$2:$C$19,2,FALSE) -> Quantity | I101: =VLOOKUP(G101,$M$2:$N$19,2,FALSE) -> d06
A102: p50 | B102: Stream Gauges | C102: Reservoirs | D102: Angelina and Neches River Authority | E102: https://www.anra.org/resources/stream_gages.html | F102: Streamflow | G102: Surface Water | H102: =VLOOKUP(G102,dataNodes!$B$2:$C$19,2,FALSE) -> Quantity | I102: =VLOOKUP(G102,$M$2:$N$19,2,FALSE) -> d13
A103: p51 | B103: Reservoir Levels | C103: Reservoirs | D103: Angelina and Neches River Authority | E103: https://www.anra.org/resources/reservoir_levels.html | F103: Reservoir levels | G103: Reservoir | H103: =VLOOKUP(G103,dataNodes!$B$2:$C$19,2,FALSE) -> Quantity | I103: =VLOOKUP(G103,$M$2:$N$19,2,FALSE) -> d11
A104: p52 | B104: In House Surface Water Quality Testing | C104: Water Quality Monitoring Program | D104: Bandera County River Authority | E104: http://www.bcragd.org/water-quality-testing/ | F104: E.coli measurements | G104: Quality | H104: =VLOOKUP(G104,dataNodes!$B$2:$C$19,2,FALSE) -> Quality | I104: =VLOOKUP(G104,$M$2:$N$19,2,FALSE) -> d03
A105: p53 | B105: Monitor Well Program | C105: Groundwater Monitoring | D105: Bandera County River Authority | E105: http://www.bcragd.org/monitor-wells/ | F105: Groundwater level | G105: Groundwater | H105: =VLOOKUP(G105,dataNodes!$B$2:$C$19,2,FALSE) -> Quantity | I105: =VLOOKUP(G105,$M$2:$N$19,2,FALSE) -> d08
A106: p54 | B106: Rainfall and River Gauges | C106: Flood Management | D106: Bandera County River Authority | E106: http://www.bcragd.org/river-gauges/ | F106: rainfall gauges | G106: Precipitation | H106: =VLOOKUP(G106,dataNodes!$B$2:$C$19,2,FALSE) -> Quantity | I106: =VLOOKUP(G106,$M$2:$N$19,2,FALSE) -> d10
A107: p54 | B107: Rainfall and River Gauges | C107: Flood Management | D107: Bandera County River Authority | E107: http://www.bcragd.org/river-gauges/ | F107: streamflow | G107: Surface Water | H107: =VLOOKUP(G107,dataNodes!$B$2:$C$19,2,FALSE) -> Quantity | I107: =VLOOKUP(G107,$M$2:$N$19,2,FALSE) -> d13
A108: p55 | B108: Medina Lake | C108: Reservoirs | D108: Bandera County River Authority | E108: http://www.bcragd.org/medina-lake/ | F108: Reservoir Levels | G108: Reservoir | H108: =VLOOKUP(G108,dataNodes!$B$2:$C$19,2,FALSE) -> Quantity | I108: =VLOOKUP(G108,$M$2:$N$19,2,FALSE) -> d11
... A122: p64 | B122: Basin Summary | C122: Water Resource Management | D122: Guadalupe Blanco River Authority | E122: http://www.gbra.org/conditions/default.aspx | F122: Reservoir elevation | G122: Reservoir | H122: =VLOOKUP(G122,dataNodes!$B$2:$C$19,2,FALSE) -> Quantity | I122: =VLOOKUP(G122,$M$2:$N$19,2,FALSE) -> d11
A123: p65 | B123: Monitoring Sites Map | C123: Clean Rivers Program | D123: Guadalupe Blanco River Authority | E123: http://www.gbra.org/crp/sites.aspx | G123: Quality | H123: =VLOOKUP(G123,dataNodes!$B$2:$C$19,2,FALSE) -> Quality | I123: =VLOOKUP(G123,$M$2:$N$19,2,FALSE) -> d03
A124: p66 | B124: Consumer Confidence Reports | C124: Water Treatment | D124: Guadalupe Blanco River Authority | E124: http://www.gbra.org/publications/ccrs.aspx | F124: Consumer Confidence Reports | G124: Regulatory | H124: =VLOOKUP(G124,dataNodes!$B$2:$C$19,2,FALSE) -> Quality | I124: =VLOOKUP(G124,$M$2:$N$19,2,FALSE) -> d04
A125: p66 | B125: Consumer Confidence Reports | C125: Water Treatment | D125: Guadalupe Blanco River Authority | E125: http://www.gbra.org/publications/ccrs.aspx | F125: Consumer Confidence Reports | G125: Utilities | H125: =VLOOKUP(G125,dataNodes!$B$2:$C$19,2,FALSE) -> Use | I125: =VLOOKUP(G125,$M$2:$N$19,2,FALSE) -> d17
A126: p67 | B126: Lavaca Regional Water Planning Group | C126: Water Delivery | D126: Lavaca Navidad River Authority | E126: http://www.lnra.org/water/lavaca-regional-water-planning-group | F126: Water plans and projections | G126: Management Plans | H126: =VLOOKUP(G126,dataNodes!$B$2:$C$19,2,FALSE) -> Use | I126: =VLOOKUP(G126,$M$2:$N$19,2,FALSE) -> d18
A127: p68 | B127: Early Warning System | C127: Instrumentation and Electronics | D127: Lavaca Navidad River Authority | E127: http://www.lnra.org/water/early-warning-system | F127: precipitation | G127: Precipitation | H127: =VLOOKUP(G127,dataNodes!$B$2:$C$19,2,FALSE) -> Quantity | I127: =VLOOKUP(G127,$M$2:$N$19,2,FALSE) -> d10
A128: p68 | B128: Early Warning System | C128: Instrumentation and Electronics | D128: Lavaca Navidad River Authority | E128: http://www.lnra.org/water/early-warning-system | F128: Stage | G128: Surface Water | H128: =VLOOKUP(G128,dataNodes!$B$2:$C$19,2,FALSE) -> Quantity | I128: =VLOOKUP(G128,$M$2:$N$19,2,FALSE) -> d13
A129: p68 | B129: Early Warning System | C129: Instrumentation and Electronics | D129: Lavaca Navidad River Authority | E129: http://www.lnra.org/water/early-warning-system | F129: Spillway and reservoir elevation | G129: Reservoir | H129: =VLOOKUP(G129,dataNodes!$B$2:$C$19,2,FALSE) -> Quantity | I129: =VLOOKUP(G129,$M$2:$N$19,2,FALSE) -> d11
A130: p68 | B130: Early Warning System | C130: Instrumentation and Electronics | D130: Lavaca Navidad River Authority | E130: http://www.lnra.org/water/early-warning-system | F130: Air temp, humidity, wind speed, direction | G130: Meteorology | H130: =VLOOKUP(G130,dataNodes!$B$2:$C$19,2,FALSE) -> Quantity | I130: =VLOOKUP(G130,$M$2:$N$19,2,FALSE) -> d09
A131: p69 | B131: Reservoir Data | C131: Reservoir | D131: Lavaca Navidad River Authority | E131: http://www.lnra.org/water/reservoir-data | F131: Rainfall | G131: Precipitation | H131: =VLOOKUP(G131,dataNodes!$B$2:$C$19,2,FALSE) -> Quantity | I131: =VLOOKUP(G131,$M$2:$N$19,2,FALSE) -> d10
A132: p69 | B132: Reservoir Data | C132: Reservoir | D132: Lavaca Navidad River Authority | E132: http://www.lnra.org/water/reservoir-data | F132: Monthly pan evaporation | G132: Evapotranspiration | H132: =VLOOKUP(G132,dataNodes!$B$2:$C$19,2,FALSE) -> Quantity | I132: =VLOOKUP(G132,$M$2:$N$19,2,FALSE) -> d05
A133: p70 | B133: Water Quality Database | C133: Clean Rivers Program | D133: Lavaca Navidad River Authority | E133: http://www.nueces-ra.org/CP/LNRA/SWQM/ | F133: Could not actually get any data to appear | G133: Quality | H133: =VLOOKUP(G133,dataNodes!$B$2:$C$19,2,FALSE) -> Quality | I133: =VLOOKUP(G133,$M$2:$N$19,2,FALSE) -> d03 | J133: Gave low discoverability score because you have to know the parameters collected to get data and it doesn't tell you.
A134: p71 | B134: LCRA Interactive Map | C134: Water | D134: Lower Colorado River Authority | E134: https://maps.lcra.org/interactive.aspx | F134: watersheds, streams | G134: Natural | H134: =VLOOKUP(G134,dataNodes!$B$2:$C$19,2,FALSE) -> Infrastructure | I134: =VLOOKUP(G134,$M$2:$N$19,2,FALSE) -> d02
...

Sheet dataEdges
A1: from | B1: to
A2: p01 | B2: d11
A3: p01 | B3: d06
A4: p02 | B4: d18
A5: p03 | B5: d18
A6: p04 | B6: d03
A7: p05 | B7: d03
A8: p06 | B8: d17
A9: p07 | B9: d17
A10: p08 | B10: d16
A11: p08 | B11: d01
A12: p09 | B12: d01
... A197: p97 | B197: d17
