Workbook

Sheet orgNodes
A1: entityID | B1: entity | C1: tier1and2entity | D1: tier1and2entityID | E1: entityIDAbove | F1: mission | G1: website | H1: operational | I1: decision | J1: regulatory | K1: research | L1: level
A2: n01 | B2: Utah | C2: Utah | D2: 1 | E2: NA | G2: https://www.utah.gov/index.html | H2: Yes | I2: Yes | J2: Yes | K2: Yes | L2: 1
A3: n02 | B3: Department of Agriculture and Food | C3: Department of Agriculture and Food | D3: 2 | E3: n01 | F3: Promote the healthy growth of Utah agriculture, conserve our natural resources and protect our food supply. | G3: https://ag.utah.gov | H3: No | I3: Yes | J3: No | K3: No | L3: 2
A4: n03 | B4: Conservation Division | C4: Department of Agriculture and Food | D4: 2 | E4: n02 | F4: Preserve and protect Utah’s soil and water resources and ensure the development and utilization for the betterment of Utah agriculture and its people. | G4: https://ag.utah.gov/farmers/conservation-division/ | H4: No | I4: Yes | J4: No | K4: No | L4: 3
A5: n04 | B5: Department of Commerce | C5: Department of Commerce | D5: 3 | E5: n01 | F5: Provide oversight of business registrations, trademarks, Uniform Commercial Code filings, occupational and professional licensing, consumer protection, public utilities, securities, real estate and residential mortgage lending. | G5: https://commerce.utah.gov/ | H5: Yes | I5: No | J5: Yes | K5: No | L5: 2
A6: n05 | B6: Division of Public Utilities | C6: Department of Commerce | D6: 3 | E6: n04 | F6: Promotes the public interest in utility regulation and works to assure that all utility customers have access to safe, reliable service at reasonable prices | G6: https://dpu.utah.gov/about.html | H6: Yes | I6: No | J6: Yes | K6: No | L6: 3
A7: n06 | B7: Water Section | C7: Department of Commerce | D7: 3 | E7: n05 | F7: Monitors and regulates numerous private water companies in Utah. | G7: https://dpu.utah.gov/utillist-water.html | H7: Yes | I7: No | J7: Yes | K7: No | L7: 4
A8: n07 | B8: Department of Environmental Quality | C8: Department of Environmental Quality | D8: 4 | E8: n01 | F8: Safeguarding and improving Utah’s air, land and water through balanced regulation. | G8: https://deq.utah.gov/ | H8: Yes | I8: Yes | J8: Yes | K8: No | L8: 2
A9: n08 | B9: Division of Drinking Water | C9: Department of Environmental Quality | D9: 4 | E9: n07 | F9: Safeguarding the quality and quantity of Utah's drinking water through balanced regulation. | G9: https://deq.utah.gov/division-drinking-water | H9: Yes | I9: No | J9: Yes | K9: No | L9: 3
A10: n09 | B10: Division of Water Quality | C10: Department of Environmental Quality | D10: 4 | E10: n07 | F10: Safeguarding and improving Utah's water through balanced regulation. | G10: https://deq.utah.gov/division-water-quality | H10: Yes | I10: No | J10: Yes | K10: No | L10: 3
A11: n10 | B11: Division of Environmental Response and Remediation | C11: Department of Environmental Quality | D11: 4 | E11: n07 | F11: Safeguarding and improving Utah’s air, land and water through balanced regulation. | G11: https://deq.utah.gov/division-environmental-response-remediation | H11: No | I11: Yes | J11: Yes | K11: No | L11: 3
A12: n11 | B12: Department of Health | C12: Department of Health | D12: 5 | E12: n01 | F12: Provides information needed to plan, implement, and evaluate interventions and programs related to the multiple goals and objectives of the Utah Department of Health. In addition, health and health care system information are made available to the public to help consumers make informed health care decisions | G12: https://health.utah.gov/ | H12: No | I12: Yes | J12: No | K12: Yes | L12: 2
A13: n12 | B13: Center for Health Data Informatics | C13: Department of Health | D13: 5 | E13: n11 | F13: Ensure Utah is a place where accurate, secure, and timely health data are available to improve health for all | G13: http://health.utah.gov/chd/ | H13: No | I13: Yes | J13: No | K13: Yes | L13: 3
A14: n13 | B14: Department of Natural Resources | C14: Department of Natural Resources | D14: 6 | E14: n01 | F14: Helps ensure the quality of life of Utah residents by managing and protecting the state's abundant natural resources | G14: https://naturalresources.utah.gov/ | H14: Yes | I14: Yes | J14: Yes | K14: Yes | L14: 2
... A46: n45 | B46: Utah Climate Center | C46: Utah State University | D46: 10 | E46: n44 | F46: Strives to provide quality climate data. | G46: https://climate.usu.edu/index.php | H46: No | I46: Yes | J46: No | K46: Yes | L46: 3

Sheet orgEdges
A1: from | B1: to
A2: n01 | B2: n02
A3: n02 | B3: n03
A4: n01 | B4: n04
A5: n04 | B5: n05
A6: n05 | B6: n06
A7: n01 | B7: n07
A8: n07 | B8: n08
A9: n07 | B9: n09
A10: n07 | B10: n10
A11: n01 | B11: n11
A12: n11 | B12: n12
... A44: n43 | B44: n44

Sheet platformNodes
A1: platformID | B1: platform | C1: entity | D1: entityID | E1: webLabel | F1: heatmapLabel | G1: tier1and2entity | H1: tier1and2entityID | I1: website | J1: easeDiscover | K1: methodDiscover | L1: easeAccess | M1: methodAccess | N1: LinktoSource | O1: fileFormat | P1: metadata | Q1: metadataFormat | R1: dataDefinitions | S1: metaAttributes | T1: metadataStandards | U1: timeliness | V1: lengthAvailable
A2: p01 | B2: Utah Open Data Catalog | C2: Technology Coordination Office - Automated Geographic Reference Center | D2: n43 | E2: AGRC | F2: =CONCATENATE(E2,": ",B2) -> AGRC: Utah Open Data Catalog | G2: =VLOOKUP($D2,orgNodes!$A$2:$D$46,3,FALSE) -> Technology Coordination Office - Automated Geographic Reference Center | H2: =VLOOKUP($D2,orgNodes!$A$2:$D$46,4,FALSE) -> 9 | I2: https://opendata.gis.utah.gov/ | J2: High | K2: Catalog | L2: Yes | M2: Web Services; Full Export | N2: Not Applicable | O2: excel; csv; geojson; shapefile; kml; geodatabase | P2: Yes | Q2: html | R2: No | S2: Descriptive; Structural | T2: Yes | U2: Varies | V2: Period of Record
A3: p02 | B3: State Geographic Information Database | C3: Technology Coordination Office - Automated Geographic Reference Center | D3: n43 | E3: AGRC | F3: =CONCATENATE(E3,": ",B3) -> AGRC: State Geographic Information Database | G3: =VLOOKUP($D3,orgNodes!$A$2:$D$46,3,FALSE) -> Technology Coordination Office - Automated Geographic Reference Center | H3: =VLOOKUP($D3,orgNodes!$A$2:$D$46,4,FALSE) -> 9 | I3: https://gis.utah.gov/#data | J3: Medium | K3: Catalog | L3: Yes | M3: Web Services; Full Export | N3: Not Applicable | O3: excel; csv; geojson; shapefile; kml; geodatabase | P3: Yes | Q3: html | R3: No | S3: Descriptive | T3: Yes | U3: Varies | V3: Current Only
A4: p03 | B4: Annual Report Archive | C4: Department of Agriculture and Food | D4: n02 | E4: UDAF | F4: =CONCATENATE(E4,": ",B4) -> UDAF: Annual Report Archive | G4: =VLOOKUP($D4,orgNodes!$A$2:$D$46,3,FALSE) -> Department of Agriculture and Food | H4: =VLOOKUP($D4,orgNodes!$A$2:$D$46,4,FALSE) -> 2 | I4: https://ag.utah.gov/about/annual-report-archive/ | J4: Low | K4: Website | L4: Yes | M4: Copy and Paste | N4: Not Applicable | O4: pdf | P4: No | Q4: No | R4: No | S4: No | T4: No | U4: Varies | V4: Limited Record
A5: p04 | B5: Salinity Control Forum | C5: Conservation Division | D5: n03 | E5: UDAF-Conservation Division | F5: =CONCATENATE(E5,": ",B5) -> UDAF-Conservation Division: Salinity Control Forum | G5: =VLOOKUP($D5,orgNodes!$A$2:$D$46,3,FALSE) -> Department of Agriculture and Food | H5: =VLOOKUP($D5,orgNodes!$A$2:$D$46,4,FALSE) -> 2 | I5: https://ag.utah.gov/farmers/conservation-division/ | J5: Low | K5: Website | L5: Yes | M5: Link to Source | N5: Direct | O5: Unknown | P5: Unknown | Q5: Unknown | R5: Unknown | S5: Unknown | T5: Unknown | U5: Unknown | V5: Unknown
A6: p05 | B6: Groundwater Program | C6: Conservation Division | D6: n03 | E6: UDAF-Conservation Division | F6: =CONCATENATE(E6,": ",B6) -> UDAF-Conservation Division: Groundwater Program | G6: =VLOOKUP($D6,orgNodes!$A$2:$D$46,3,FALSE) -> Department of Agriculture and Food | H6: =VLOOKUP($D6,orgNodes!$A$2:$D$46,4,FALSE) -> 2 | I6: https://ag.utah.gov/farmers/conservation-division/ | J6: Low | K6: Website | L6: Yes | M6: Individual Export | N6: Not Applicable | O6: pdf | P6: Yes | Q6: in data | R6: Yes | S6: Administrative; Descriptive | T6: No | U6: Yearly or Higher | V6: Limited Record
A7: p06 | B7: Harmful Algal Blooms | C7: Conservation Division | D7: n03 | E7: UDAF-Conservation Division | F7: =CONCATENATE(E7,": ",B7) -> UDAF-Conservation Division: Harmful Algal Blooms | G7: =VLOOKUP($D7,orgNodes!$A$2:$D$46,3,FALSE) -> Department of Agriculture and Food | H7: =VLOOKUP($D7,orgNodes!$A$2:$D$46,4,FALSE) -> 2 | I7: https://ag.utah.gov/farmers/conservation-division/harmful-algal-blooms/ | J7: Medium | K7: Map | L7: Yes | M7: Copy and Paste | N7: Not Applicable | O7: html | P7: Yes | Q7: html | R7: No | S7: Descriptive | T7: No | U7: Monthly or higher | V7: Limited Record
A8: p07 | B8: Locate Utility Company | C8: Division of Public Utilities | D8: n05 | E8: UDOC-Public Utilities Division | F8: =CONCATENATE(E8,": ",B8) -> UDOC-Public Utilities Division: Locate Utility Company | G8: =VLOOKUP($D8,orgNodes!$A$2:$D$46,3,FALSE) -> Department of Commerce | H8: =VLOOKUP($D8,orgNodes!$A$2:$D$46,4,FALSE) -> 3 | I8: http://utah.maps.arcgis.com/apps/Viewer/index.html?appid=573dfdb6220d4fada6d833def633b866 | J8: Medium | K8: Map | L8: No | M8: None | N8: Not Applicable | O8: None | P8: No | Q8: No | R8: No | S8: No | T8: No | U8: Unknown | V8: Current Only
A9: p08 | B9: Water Utilities | C9: Division of Public Utilities | D9: n05 | E9: UDOC-Public Utilities Division | F9: =CONCATENATE(E9,": ",B9) -> UDOC-Public Utilities Division: Water Utilities | G9: =VLOOKUP($D9,orgNodes!$A$2:$D$46,3,FALSE) -> Department of Commerce | H9: =VLOOKUP($D9,orgNodes!$A$2:$D$46,4,FALSE) -> 3 | I9: https://dpu.utah.gov/utillist-water.html | J9: High | K9: Website | L9: Yes | M9: Copy and Paste; Individual Export | N9: Not Applicable | O9: html; pdf | P9: Yes | Q9: pdf | R9: No | S9: Administrative; Descriptive | T9: No | U9: Varies | V9: Limited Record
A10: p09 | B10: Environmental Interactive Map | C10: Department of Environmental Quality | D10: n07 | E10: UDEQ | F10: =CONCATENATE(E10,": ",B10) -> UDEQ: Environmental Interactive Map | G10: =VLOOKUP($D10,orgNodes!$A$2:$D$46,3,FALSE) -> Department of Environmental Quality | H10: =VLOOKUP($D10,orgNodes!$A$2:$D$46,4,FALSE) -> 4 | I10: https://enviro.deq.utah.gov/ | J10: High | K10: Map; Catalog | L10: Yes; Registration Required | M10: Batch Export; Full Export | N10: Not Applicable | O10: excel; csv; geodatabase; shapefile | P10: No | Q10: No | R10: No | S10: No | T10: No | U10: Daily or Higher | V10: Limited Record
A11: p10 | B11: Regulatory/Policy Documents | C11: Department of Environmental Quality | D11: n07 | E11: UDEQ | F11: =CONCATENATE(E11,": ",B11) -> UDEQ: Regulatory/Policy Documents | G11: =VLOOKUP($D11,orgNodes!$A$2:$D$46,3,FALSE) -> Department of Environmental Quality | H11: =VLOOKUP($D11,orgNodes!$A$2:$D$46,4,FALSE) -> 4 | I11: http://eqedocs.utah.gov/ | J11: High | K11: Map; Catalog | L11: Yes | M11: Individual Export | N11: Not Applicable | O11: pdf | P11: Yes | Q11: html | R11: No | S11: Descriptive | T11: No | U11: Daily or Higher | V11: Limited Record
A12: p11 | B12: Waterlink Database | C12: Division of Drinking Water | D12: n08 | E12: UDEQ-Drinking Water | F12: =CONCATENATE(E12,": ",B12) -> UDEQ-Drinking Water: Waterlink Database | G12: =VLOOKUP($D12,orgNodes!$A$2:$D$46,3,FALSE) -> Department of Environmental Quality | H12: =VLOOKUP($D12,orgNodes!$A$2:$D$46,4,FALSE) -> 4 | I12: https://waterlink.utah.gov/deqWater/ | J12: High | K12: Catalog | L12: Yes | M12: Individual Export | N12: Not Applicable | O12: html; pdf | P12: No | Q12: No | R12: No | S12: No | T12: No | U12: Monthly or higher | V12: Limited Record
A13: p12 | B13: Ambient Water Quality Monitoring System (AWQMS ) | C13: Division of Water Quality | D13: n09 | E13: UDEQ-Water Quality | F13: =CONCATENATE(E13,": ",B13) -> UDEQ-Water Quality: Ambient Water Quality Monitoring System (AWQMS ) | G13: =VLOOKUP($D13,orgNodes!$A$2:$D$46,3,FALSE) -> Department of Environmental Quality | H13: =VLOOKUP($D13,orgNodes!$A$2:$D$46,4,FALSE) -> 4 | I13: https://awqms3.goldsystems.com/Login.aspx | J13: High | K13: Unknown | L13: Permission Required | M13: Unknown | N13: Not Applicable | O13: Unknown | P13: Unknown | Q13: Unknown | R13: Unknown | S13: Unknown | T13: Unknown | U13: Unknown | V13: Unknown
... A64: p63 | B64: Agweather | C64: Utah Climate Center | D64: n45 | E64: Climate Center | F64: =CONCATENATE(E64,": ",B64) -> Climate Center: Agweather | G64: =VLOOKUP($D64,orgNodes!$A$2:$D$46,3,FALSE) -> Utah State University | H64: =VLOOKUP($D64,orgNodes!$A$2:$D$46,4,FALSE) -> 10 | I64: https://climate.usu.edu/mchd/index.php | J64: High | K64: Map; Catalog | L64: Yes | M64: Individual Export; Copy and Paste | N64: Not Applicable | O64: html; csv | P64: Yes | Q64: in data | R64: No | S64: Descriptive | T64: No | U64: Daily or Higher | V64: Period of Record
A65: p64 | B65: Climate Data | C65: Utah Climate Center | D65: n45 | E65: Climate Center | F65: =CONCATENATE(E65,": ",B65) -> Climate Center: Climate Data | G65: =VLOOKUP($D65,orgNodes!$A$2:$D$46,3,FALSE) -> Utah State University | H65: 10 | I65: https://climate.usu.edu/mapGUI/mapGUI.php | J65: High | K65: Map; Catalog | L65: Yes | M65: Individual Export; Batch Export | N65: Not Applicable | O65: html; csv; pdf | P65: Yes | Q65: in data | R65: No | S65: Administrative | T65: No | U65: Daily or Higher | V65: Period of Record

Sheet dataNodeTypes
A1: platformID | B1: platform | C1: entity | D1: tier1and2entity | E1: website | F1: data | G1: dataGroup | H1: dataCategory | I1: dataID | J1: notes | M1: dataGroup - linked to dataNodes tab | N1: dataID - linked to dataNodes tab
A2: p01 | B2: Utah Open Data Catalog | C2: Technology Coordination Office - Automated Geographic Reference Center | D2: Technology Coordination Office - Automated Geographic Reference Center | E2: https://opendata.gis.utah.gov/ | F2: streams; hucs; lakes; aquifer | G2: Natural | H2: Infrastructure | I2: =VLOOKUP(G2,$M$4:$N$21,2,FALSE) -> d02
A3: p01 | B3: Utah Open Data Catalog | C3: Technology Coordination Office - Automated Geographic Reference Center | D3: Technology Coordination Office - Automated Geographic Reference Center | E3: https://opendata.gis.utah.gov/ | F3: well logs; point of diversion; | G3: Groundwater | H3: Quantity | I3: =VLOOKUP(G3,$M$4:$N$21,2,FALSE) -> d08
A4: p01 | B4: Utah Open Data Catalog | C4: Technology Coordination Office - Automated Geographic Reference Center | D4: Technology Coordination Office - Automated Geographic Reference Center | E4: https://opendata.gis.utah.gov/ | F4: water service areas; points of diversion; water pumps; canals; dam locations | G4: Built | H4: Infrastructure | I4: =VLOOKUP(G4,$M$4:$N$21,2,FALSE) -> d01 | M4: =dataNodes!B2 -> Built | N4: =dataNodes!A2 -> d01
A5: p01 | B5: Utah Open Data Catalog | C5: Technology Coordination Office - Automated Geographic Reference Center | D5: Technology Coordination Office - Automated Geographic Reference Center | E5: https://opendata.gis.utah.gov/ | F5: water rights; | G5: Use | H5: Use | I5: =VLOOKUP(G5,$M$4:$N$21,2,FALSE) -> d16 | M5: =dataNodes!B3 -> Natural | N5: =dataNodes!A3 -> d02
A6: p01 | B6: Utah Open Data Catalog | C6: Technology Coordination Office - Automated Geographic Reference Center | D6: Technology Coordination Office - Automated Geographic Reference Center | E6: https://opendata.gis.utah.gov/ | F6: duty values; irrigation | G6: Irrigation | H6: Use | I6: =VLOOKUP(G6,$M$4:$N$21,2,FALSE) -> d15 | M6: =dataNodes!B4 -> Quality | N6: =dataNodes!A4 -> d03
A7: p01 | B7: Utah Open Data Catalog | C7: Technology Coordination Office - Automated Geographic Reference Center | D7: Technology Coordination Office - Automated Geographic Reference Center | E7: https://opendata.gis.utah.gov/ | F7: great lake flooding; floodplains | G7: Extreme Events | H7: Quantity | I7: =VLOOKUP(G7,$M$4:$N$21,2,FALSE) -> d06 | M7: =dataNodes!B5 -> Regulatory | N7: =dataNodes!A5 -> d04
A8: p01 | B8: Utah Open Data Catalog | C8: Technology Coordination Office - Automated Geographic Reference Center | D8: Technology Coordination Office - Automated Geographic Reference Center | E8: https://opendata.gis.utah.gov/ | F8: dam inundation levels | G8: reservoir | H8: Quantity | I8: =VLOOKUP(G8,$M$4:$N$21,2,FALSE) -> d11 | M8: =dataNodes!B6 -> Evapotranspiration | N8: =dataNodes!A6 -> d05
A9: p01 | B9: Utah Open Data Catalog | C9: Technology Coordination Office - Automated Geographic Reference Center | D9: Technology Coordination Office - Automated Geographic Reference Center | E9: https://opendata.gis.utah.gov/ | F9: water quality assessment of lakes and streams | G9: Quality | H9: Quality | I9: =VLOOKUP(G9,$M$4:$N$21,2,FALSE) -> d03 | M9: =dataNodes!B7 -> Extreme Events | N9: =dataNodes!A7 -> d06
A10: p02 | B10: State Geographic Information Database | C10: Technology Coordination Office - Automated Geographic Reference Center | D10: Technology Coordination Office - Automated Geographic Reference Center | E10: https://gis.utah.gov/#data | F10: streams; hucs; lakes; aquifer | G10: Natural | H10: Infrastructure | I10: =VLOOKUP(G10,$M$4:$N$21,2,FALSE) -> d02 | M10: =dataNodes!B8 -> Glacial and Snow | N10: =dataNodes!A8 -> d07
A11: p02 | B11: State Geographic Information Database | C11: Technology Coordination Office - Automated Geographic Reference Center | D11: Technology Coordination Office - Automated Geographic Reference Center | E11: https://gis.utah.gov/#data | F11: water service areas; points of diversion; water pumps; canals; dam locations | G11: Built | H11: Infrastructure | I11: =VLOOKUP(G11,$M$4:$N$21,2,FALSE) -> d01 | M11: =dataNodes!B9 -> Groundwater | N11: =dataNodes!A9 -> d08
A12: p02 | B12: State Geographic Information Database | C12: Technology Coordination Office - Automated Geographic Reference Center | D12: Technology Coordination Office - Automated Geographic Reference Center | E12: https://gis.utah.gov/#data | F12: water rights; | G12: Use | H12: Use | I12: =VLOOKUP(G12,$M$4:$N$21,2,FALSE) -> d16 | M12: =dataNodes!B10 -> Meteorology | N12: =dataNodes!A10 -> d09
A13: p02 | B13: State Geographic Information Database | C13: Technology Coordination Office - Automated Geographic Reference Center | D13: Technology Coordination Office - Automated Geographic Reference Center | E13: https://gis.utah.gov/#data | F13: duty values; irrigation | G13: Irrigation | H13: Use | I13: =VLOOKUP(G13,$M$4:$N$21,2,FALSE) -> d15 | M13: =dataNodes!B11 -> Precipitation | N13: =dataNodes!A11 -> d10
A14: p02 | B14: State Geographic Information Database | C14: Technology Coordination Office - Automated Geographic Reference Center | D14: Technology Coordination Office - Automated Geographic Reference Center | E14: https://gis.utah.gov/#data | F14: great lake flooding; floodplains | G14: Extreme Events | H14: Quantity | I14: =VLOOKUP(G14,$M$4:$N$21,2,FALSE) -> d06 | M14: =dataNodes!B12 -> Reservoir | N14: =dataNodes!A12 -> d11
A15: p02 | B15: State Geographic Information Database | C15: Technology Coordination Office - Automated Geographic Reference Center | D15: Technology Coordination Office - Automated Geographic Reference Center | E15: https://gis.utah.gov/#data | F15: dam inundation levels | G15: reservoir | H15: Quantity | I15: =VLOOKUP(G15,$M$4:$N$21,2,FALSE) -> d11 | M15: =dataNodes!B13 -> Soil | N15: =dataNodes!A13 -> d12
A16: p02 | B16: State Geographic Information Database | C16: Technology Coordination Office - Automated Geographic Reference Center | D16: Technology Coordination Office - Automated Geographic Reference Center | E16: https://gis.utah.gov/#data | F16: water quality assessment of lakes and streams | G16: Quality | H16: Quality | I16: =VLOOKUP(G16,$M$4:$N$21,2,FALSE) -> d03 | M16: =dataNodes!B14 -> Surface Water | N16: =dataNodes!A14 -> d13
A17: p02 | B17: State Geographic Information Database | C17: Technology Coordination Office - Automated Geographic Reference Center | D17: =VLOOKUP($D17,orgNodes!$A$2:$D$46,3,FALSE) -> Department of Agriculture and Food | E17: https://ag.utah.gov/about/annual-report-archive/ | F17: Water & irrigation costs; irrigated acres | G17: Irrigation | H17: Use | I17: =VLOOKUP(G17,$M$4:$N$21,2,FALSE) -> d15 | M17: =dataNodes!B15 -> Hydropower | N17: =dataNodes!A15 -> d14
A18: p03 | B18: Annual Report Archive | C18: Department of Agriculture and Food | D18: Department of Agriculture and Food | E18: http://www.coloradoriversalinity.org/documents.php?ctgy=Reclamation | F18: Salinity | G18: Quality | H18: Quality | I18: =VLOOKUP(G18,$M$4:$N$21,2,FALSE) -> d03 | M18: =dataNodes!B16 -> Irrigation | N18: =dataNodes!A16 -> d15
A19: p04 | B19: =platformNodes!B5 -> Salinity Control Forum | C19: =platformNodes!C5 -> Conservation Division | D19: Department of Agriculture and Food | E19: https://ag.utah.gov/farmers/conservation-division/ | F19: groundwater locations; site condition; sample site; well head; well casing | G19: Built | H19: Infrastructure | I19: =VLOOKUP(G19,$M$4:$N$21,2,FALSE) -> d01 | M19: =dataNodes!B17 -> Use | N19: =dataNodes!A17 -> d16
A20: p05 | B20: Groundwater Program | C20: Conservation Division | D20: Department of Agriculture and Food | E20: https://ag.utah.gov/farmers/conservation-division/ | F20: coliforms; temperature, conductivity; TSS; hardness | G20: Quality | H20: Quality | I20: =VLOOKUP(G20,$M$4:$N$21,2,FALSE) -> d03 | M20: =dataNodes!B18 -> Utilities | N20: =dataNodes!A18 -> d17
A21: p06 | B21: Harmful Algal Blooms | C21: Conservation Division | D21: Department of Agriculture and Food | E21: https://ag.utah.gov/farmers/conservation-division/harmful-algal-blooms/ | F21: Harmful algal blooms map | G21: Quality | H21: Quality | I21: =VLOOKUP(G21,$M$4:$N$21,2,FALSE) -> d03 | M21: =dataNodes!B19 -> Management Plans | N21: =dataNodes!A19 -> d18
A22: p07 | B22: Locate Utility Company | C22: Division of Public Utilities | D22: Department of Commerce | E22: http://utah.maps.arcgis.com/apps/Viewer/index.html?appid=573dfdb6220d4fada6d833def633b866 | F22: Water utility service areas | G22: Built | H22: Infrastructure | I22: =VLOOKUP(G22,$M$4:$N$21,2,FALSE) -> d01
A23: p08 | B23: Water Utilities | C23: Division of Public Utilities | D23: Department of Commerce | E23: https://dpu.utah.gov/utillist-water.html | F23: Utility Information; Rates | G23: Utilities | H23: Use | I23: =VLOOKUP(G23,$M$4:$N$21,2,FALSE) -> d17
A24: p09 | B24: Environmental Interactive Map | C24: Department of Environmental Quality | D24: Department of Environmental Quality | E24: https://enviro.deq.utah.gov/ | F24: watershed boundaries | G24: Natural | H24: Infrastructure | I24: =VLOOKUP(G24,$M$4:$N$21,2,FALSE) -> d02
A25: p09 | B25: Environmental Interactive Map | C25: Department of Environmental Quality | D25: Department of Environmental Quality | E25: https://enviro.deq.utah.gov/ | F25: points of diversion; NPDES locations; Public Water Systems; monitoring locations | G25: Built | H25: Infrastructure | I25: =VLOOKUP(G25,$M$4:$N$21,2,FALSE) -> d01
A26: p09 | B26: Environmental Interactive Map | C26: Department of Environmental Quality | D26: Department of Environmental Quality | E26: https://enviro.deq.utah.gov/ | F26: groundwater permits; water rights; NPDES discharges | G26: Regulatory | H26: Quality | I26: =VLOOKUP(G26,$M$4:$N$21,2,FALSE) -> d04
A27: p09 | B27: Environmental Interactive Map | C27: Department of Environmental Quality | D27: Department of Environmental Quality | E27: https://enviro.deq.utah.gov/ | F27: water rights; | G27: Use | H27: Use | I27: =VLOOKUP(G27,$M$4:$N$21,2,FALSE) -> d16
A28: p09 | B28: Environmental Interactive Map | C28: Department of Environmental Quality | D28: Department of Environmental Quality | E28: https://enviro.deq.utah.gov/ | F28: Assessed lakes and waters; mercury in fish | G28: Quality | H28: Quality | I28: =VLOOKUP(G28,$M$4:$N$21,2,FALSE) -> d03
A29: p09 | B29: Environmental Interactive Map | C29: Department of Environmental Quality | D29: Department of Environmental Quality | E29: https://enviro.deq.utah.gov/ | F29: UIC; Groundwater Projection Zones | G29: Groundwater | H29: Quantity | I29: =VLOOKUP(G29,$M$4:$N$21,2,FALSE) -> d08
A30: p09 | B30: Environmental Interactive Map | C30: Department of Environmental Quality | D30: Department of Environmental Quality | E30: https://enviro.deq.utah.gov/ | F30: Drinking Water | G30: Utilities | H30: Use | I30: =VLOOKUP(G30,$M$4:$N$21,2,FALSE) -> d17
A31: p09 | B31: Environmental Interactive Map | C31: Department of Environmental Quality | D31: Department of Environmental Quality | E31: https://enviro.deq.utah.gov/ | F31: Irrigated Crop Consumptive Zones | G31: Irrigation | H31: Use | I31: =VLOOKUP(G31,$M$4:$N$21,2,FALSE) -> d15
A32: p10 | B32: Regulatory/Policy Documents | C32: Department of Environmental Quality | D32: Department of Environmental Quality | E32: http://eqedocs.utah.gov/ | F32: DEQ scanned documents on policies/regulations | G32: Regulatory | H32: Quality | I32: =VLOOKUP(G32,$M$4:$N$21,2,FALSE) -> d04
A33: p11 | B33: Waterlink Database | C33: Division of Drinking Water | D33: Department of Environmental Quality | E33: https://waterlink.utah.gov/deqWater/ | F33: Regulatory Water Quality | G33: Regulatory | H33: Quality | I33: =VLOOKUP(G33,$M$4:$N$21,2,FALSE) -> d04
... A161: p64 | B161: Climate Data | C161: Utah Climate Center | D161: Utah State University | E161: https://climate.usu.edu/mapGUI/mapGUI.php | F161: precipitation | G161: Precipitation | H161: Quantity | I161: =VLOOKUP(G161,$M$4:$N$21,2,FALSE) -> d10

Sheet dataEdges
A1: from | B1: to
A2: p01 | B2: d02
A3: p01 | B3: d08
A4: p01 | B4: d01
A5: p01 | B5: d16
A6: p01 | B6: d15
A7: p01 | B7: d06
A8: p01 | B8: d11
A9: p01 | B9: d03
A10: p02 | B10: d02
A11: p02 | B11: d01
A12: p02 | B12: d16
... A158: p64 | B158: d10

Sheet dataNodes
A1: dataID | B1: dataGroup | C1: dataCategory
A2: d01 | B2: Built | C2: Infrastructure
A3: d02 | B3: Natural | C3: Infrastructure
A4: d03 | B4: Quality | C4: Quality
A5: d04 | B5: Regulatory | C5: Quality
A6: d05 | B6: Evapotranspiration | C6: Quantity
A7: d06 | B7: Extreme Events | C7: Quantity
A8: d07 | B8: Glacial and Snow | C8: Quantity
A9: d08 | B9: Groundwater | C9: Quantity
A10: d09 | B10: Meteorology | C10: Quantity
A11: d10 | B11: Precipitation | C11: Quantity
A12: d11 | B12: Reservoir | C12: Quantity
... A19: d18 | B19: Management Plans | C19: Use
